components/adder/adder.v
// Created by Kavan Heppenstall, 22/08/2024

module adder1bit(A, B, C_in, S, C_out);

input A, B, C_in;
output S, C_out;

assign S = A + B + C_in;

assign C_out = (A & B) | (A & C_in) | (B & C_in);

endmodule

module adder4bit(A, B, C_in, S, C_out);

input [3:0] A, B;
input C_in;

output [3:0] S;
output C_out;

wire [3:0] C_internal;

adder1bit A0(.A(A[0]), .B(B[0]), .C_in(C_in), .S(S[0]), .C_out(C_internal[0]));

adder1bit A1(.A(A[1]), .B(B[1]), .C_in(C_internal[0]), .S(S[1]), .C_out(C_internal[1]));

adder1bit A2(.A(A[2]), .B(B[2]), .C_in(C_internal[1]), .S(S[2]), .C_out(C_internal[2]));

adder1bit A3(.A(A[3]), .B(B[3]), .C_in(C_internal[2]), .S(S[3]), .C_out(C_out));


endmodule

module adder16bit(A, B, C_in, S, C_out);

    input [15:0] A, B;
    input C_in;

    output [15:0] S;
    output C_out;

    wire [3:0] C_internal;

    adder4bit A0(.A(A[3:0]), .B(B[3:0]), .C_in(C_in), .S(S[3:0]), .C_out(C_internal[0]));
    
    adder4bit A1(.A(A[7:4]), .B(B[7:4]), .C_in(C_internal[0]), .S(S[7:4]), .C_out(C_internal[1]));
    
    adder4bit A2(.A(A[11:8]), .B(B[11:8]), .C_in(C_internal[1]), .S(S[11:8]), .C_out(C_internal[2]));
    
    adder4bit A3(.A(A[15:12]), .B(B[15:12]), .C_in(C_internal[2]), .S(S[15:12]), .C_out(C_out));


endmodule

components/adder/adder16bit_tb.v
// Created by Kavan Heppenstall, 22/08/2024

`timescale 1ns/1ns
`include "adder.v"

module adder16bit_tb;

reg [15:0] A, B;
reg C_in;

wire [15:0] S;
wire C_out;

integer i, j;

adder16bit dut(A, B, C_in, S, C_out);

initial begin
    
    $dumpfile("adder16bit_tb.vcd");
    $dumpvars(0, adder16bit_tb);

    #20;

    for (i = 0; i < 100; i = i + 1) begin
        
        for (j = 0; j < 100; j = j + 1) begin
            
            A = i; B = j; C_in = 1'b0; #20;
            
            A = i; B = j; C_in = 1'b1; #20;

        end

    end


    $display("end");

end


endmodule

components/adder/adder16bit_tb.vcd
$date
	Thu Aug 22 14:52:17 2024
$end
$version
	Icarus Verilog
$end
$timescale
	1ns
$end
$scope module adder16bit_tb $end
$var wire 16 ! S [15:0] $end
$var wire 1 " C_out $end
$var reg 16 # A [15:0] $end
$var reg 16 $ B [15:0] $end
$var reg 1 % C_in $end
$var integer 32 & i [31:0] $end
$var integer 32 ' j [31:0] $end
$scope module dut $end
$var wire 16 ( A [15:0] $end
$var wire 16 ) B [15:0] $end
$var wire 1 % C_in $end
$var wire 16 * S [15:0] $end
$var wire 1 " C_out $end
$var wire 4 + C_internal [3:0] $end
$scope module A0 $end
$var wire 4 , A [3:0] $end
$var wire 4 - B [3:0] $end
$var wire 1 % C_in $end
$var wire 4 . S [3:0] $end
$var wire 1 / C_out $end
$var wire 4 0 C_internal [3:0] $end
$scope module A0 $end
$var wire 1 1 A $end
$var wire 1 2 B $end
$var wire 1 % C_in $end
$var wire 1 3 C_out $end
$var wire 1 4 S $end
$upscope $end
$scope module A1 $end
$var wire 1 5 A $end
$var wire 1 6 B $end
$var wire 1 7 C_in $end
$var wire 1 8 C_out $end
$var wire 1 9 S $end
$upscope $end
$scope module A2 $end
$var wire 1 : A $end
$var wire 1 ; B $end
$var wire 1 < C_in $end
$var wire 1 = C_out $end
$var wire 1 > S $end
$upscope $end
$scope module A3 $end
$var wire 1 ? A $end
$var wire 1 @ B $end
$var wire 1 A C_in $end
$var wire 1 / C_out $end
$var wire 1 B S $end
$upscope $end
$upscope $end
$scope module A1 $end
$var wire 4 C A [3:0] $end
$var wire 4 D B [3:0] $end
$var wire 1 E C_in $end
$var wire 4 F S [3:0] $end
$var wire 1 G C_out $end
$var wire 4 H C_internal [3:0] $end
$scope module A0 $end
$var wire 1 I A $end
$var wire 1 J B $end
$var wire 1 E C_in $end
$var wire 1 K C_out $end
$var wire 1 L S $end
$upscope $end
$scope module A1 $end
$var wire 1 M A $end
$var wire 1 N B $end
$var wire 1 O C_in $end
$var wire 1 P C_out $end
$var wire 1 Q S $end
$upscope $end
$scope module A2 $end
$var wire 1 R A $end
$var wire 1 S B $end
$var wire 1 T C_in $end
$var wire 1 U C_out $end
$var wire 1 V S $end
$upscope $end
$scope module A3 $end
$var wire 1 W A $end
$var wire 1 X B $end
$var wire 1 Y C_in $end
$var wire 1 G C_out $end
$var wire 1 Z S $end
$upscope $end
$upscope $end
$scope module A2 $end
$var wire 4 [ A [3:0] $end
$var wire 4 \ B [3:0] $end
$var wire 1 ] C_in $end
$var wire 4 ^ S [3:0] $end
$var wire 1 _ C_out $end
$var wire 4 ` C_internal [3:0] $end
$scope module A0 $end
$var wire 1 a A $end
$var wire 1 b B $end
$var wire 1 ] C_in $end
$var wire 1 c C_out $end
$var wire 1 d S $end
$upscope $end
$scope module A1 $end
$var wire 1 e A $end
$var wire 1 f B $end
$var wire 1 g C_in $end
$var wire 1 h C_out $end
$var wire 1 i S $end
$upscope $end
$scope module A2 $end
$var wire 1 j A $end
$var wire 1 k B $end
$var wire 1 l C_in $end
$var wire 1 m C_out $end
$var wire 1 n S $end
$upscope $end
$scope module A3 $end
$var wire 1 o A $end
$var wire 1 p B $end
$var wire 1 q C_in $end
$var wire 1 _ C_out $end
$var wire 1 r S $end
$upscope $end
$upscope $end
$scope module A3 $end
$var wire 4 s A [3:0] $end
$var wire 4 t B [3:0] $end
$var wire 1 u C_in $end
$var wire 4 v S [3:0] $end
$var wire 1 " C_out $end
$var wire 4 w C_internal [3:0] $end
$scope module A0 $end
$var wire 1 x A $end
$var wire 1 y B $end
$var wire 1 u C_in $end
$var wire 1 z C_out $end
$var wire 1 { S $end
$upscope $end
$scope module A1 $end
$var wire 1 | A $end
$var wire 1 } B $end
$var wire 1 ~ C_in $end
$var wire 1 !" C_out $end
$var wire 1 "" S $end
$upscope $end
$scope module A2 $end
$var wire 1 #" A $end
$var wire 1 $" B $end
$var wire 1 %" C_in $end
$var wire 1 &" C_out $end
$var wire 1 '" S $end
$upscope $end
$scope module A3 $end
$var wire 1 (" A $end
$var wire 1 )" B $end
$var wire 1 *" C_in $end
$var wire 1 " C_out $end
$var wire 1 +" S $end
$upscope $end
$upscope $end
$upscope $end
$upscope $end
$enddefinitions $end
$comment Show the parameter values. $end
$dumpall
$end
#0
$dumpvars
x+"
x*"
x)"
x("
x'"
x&"
x%"
x$"
x#"
x""
x!"
x~
x}
x|
x{
xz
xy
xx
bzxxx w
bx v
xu
bx t
bx s
xr
xq
xp
xo
xn
xm
xl
xk
xj
xi
xh
xg
xf
xe
xd
xc
xb
xa
bzxxx `
x_
bx ^
x]
bx \
bx [
xZ
xY
xX
xW
xV
xU
xT
xS
xR
xQ
xP
xO
xN
xM
xL
xK
xJ
xI
bzxxx H
xG
bx F
xE
bx D
bx C
xB
xA
x@
x?
x>
x=
x<
x;
x:
x9
x8
x7
x6
x5
x4
x3
x2
x1
bzxxx 0
x/
bx .
bx -
bx ,
bzxxx +
bx *
bx )
bx (
bx '
bx &
x%
bx $
bx #
x"
bx !
$end
#20
09
07
0>
0<
0B
0A
0L
0E
0Q
0O
0V
0T
b0 F
0Z
0Y
0d
0]
0i
0g
0n
0l
b0 ^
0r
0q
0{
0u
0""
0~
0'"
0%"
b0 v
0+"
0*"
03
08
bz000 0
0=
0/
0K
0P
bz000 H
0U
0G
0c
0h
bz000 `
0m
bz000 +
0_
0z
0!"
bz000 w
0&"
0"
b0 !
b0 *
b0 .
04
02
06
0;
0@
0J
0N
0S
0X
0b
0f
0k
0p
0y
0}
0$"
0)"
01
05
0:
0?
0I
0M
0R
0W
0a
0e
0j
0o
0x
0|
0#"
0("
b0 -
b0 D
b0 \
b0 t
b0 ,
b0 C
b0 [
b0 s
0%
b0 $
b0 )
b0 #
b0 (
b0 '
b0 &
#40
b1 !
b1 *
b1 .
14
1%
#60
12
b1 -
b1 !
b1 *
b1 .
14
0%
b1 $
b1 )
b1 '
#80
19
17
bz001 0
13
b10 !
b10 *
b10 .
04
1%
#100
0>
0<
08
07
bz000 0
03
02
19
16
b10 -
b10 !
b10 *
b10 .
04
0%
b10 $
b10 )
b10 '
#120
b11 !
b11 *
b11 .
14
1%
#140
12
b11 -
b11 !
b11 *
b11 .
14
0%
b11 $
b11 )
b11 '
#160
1>
1<
18
09
17
bz011 0
13
b100 !
b100 *
b100 .
04
1%
#180
0<
0B
0A
08
0=
07
bz000 0
03
02
09
06
1>
1;
b100 -
b100 !
b100 *
b100 .
04
0%
b100 $
b100 )
b100 '
#200
b101 !
b101 *
b101 .
14
1%
#220
12
b101 -
b101 !
b101 *
b101 .
14
0%
b101 $
b101 )
b101 '
#240
19
17
bz001 0
13
b110 !
b110 *
b110 .
04
1%
#260
0B
0A
0=
1>
0<
08
07
bz000 0
03
02
19
16
b110 -
b110 !
b110 *
b110 .
04
0%
b110 $
b110 )
b110 '
#280
b111 !
b111 *
b111 .
14
1%
#300
12
b111 -
b111 !
b111 *
b111 .
14
0%
b111 $
b111 )
b111 '
#320
1B
1A
1=
0>
1<
18
09
17
bz111 0
13
b1000 !
b1000 *
b1000 .
04
1%
#340
0<
0A
b0 F
0L
0E
08
0=
bz000 +
0/
07
bz000 0
03
02
09
06
0>
0;
1B
1@
b1000 -
b1000 !
b1000 *
b1000 .
04
0%
b1000 $
b1000 )
b1000 '
#360
b1001 !
b1001 *
b1001 .
14
1%
#380
12
b1001 -
b1001 !
b1001 *
b1001 .
14
0%
b1001 $
b1001 )
b1001 '
#400
19
17
bz001 0
13
b1010 !
b1010 *
b1010 .
04
1%
#420
0>
0<
08
07
bz000 0
03
02
19
16
b1010 -
b1010 !
b1010 *
b1010 .
04
0%
b1010 $
b1010 )
b1010 '
#440
b1011 !
b1011 *
b1011 .
14
1%
#460
12
b1011 -
b1011 !
b1011 *
b1011 .
14
0%
b1011 $
b1011 )
b1011 '
#480
1>
1<
18
09
17
bz011 0
13
b1100 !
b1100 *
b1100 .
04
1%
#500
b0 F
0L
0E
bz000 +
0/
0<
1B
0A
08
0=
07
bz000 0
03
02
09
06
1>
1;
b1100 -
b1100 !
b1100 *
b1100 .
04
0%
b1100 $
b1100 )
b1100 '
#520
b1101 !
b1101 *
b1101 .
14
1%
#540
12
b1101 -
b1101 !
b1101 *
b1101 .
14
0%
b1101 $
b1101 )
b1101 '
#560
19
17
bz001 0
13
b1110 !
b1110 *
b1110 .
04
1%
#580
b0 F
0L
0E
bz000 +
0/
1B
0A
0=
1>
0<
08
07
bz000 0
03
02
19
16
b1110 -
b1110 !
b1110 *
b1110 .
04
0%
b1110 $
b1110 )
b1110 '
#600
b1111 !
b1111 *
b1111 .
14
1%
#620
12
b1111 -
b1111 !
b1111 *
b1111 .
14
0%
b1111 $
b1111 )
b1111 '
#640
b1 F
1L
1E
bz001 +
1/
0B
1A
1=
0>
1<
18
09
17
bz111 0
13
b10000 !
b10000 *
b0 .
04
1%
#660
0<
0A
0E
0Q
0O
08
0=
bz000 +
0/
bz000 H
0K
07
bz000 0
03
02
09
06
0>
0;
0B
0@
b1 F
1L
1J
b0 -
b1 D
b10000 !
b10000 *
b0 .
04
0%
b10000 $
b10000 )
b10000 '
#680
b10001 !
b10001 *
b1 .
14
1%
#700
12
b1 -
b10001 !
b10001 *
b1 .
14
0%
b10001 $
b10001 )
b10001 '
#720
19
17
bz001 0
13
b10010 !
b10010 *
b10 .
04
1%
#740
0>
0<
08
07
bz000 0
03
02
19
16
b10 -
b10010 !
b10010 *
b10 .
04
0%
b10010 $
b10010 )
b10010 '
#760
b10011 !
b10011 *
b11 .
14
1%
#780
12
b11 -
b10011 !
b10011 *
b11 .
14
0%
b10011 $
b10011 )
b10011 '
#800
1>
1<
18
09
17
bz011 0
13
b10100 !
b10100 *
b100 .
04
1%
#820
0<
0B
0A
08
0=
07
bz000 0
03
02
09
06
1>
1;
b100 -
b10100 !
b10100 *
b100 .
04
0%
b10100 $
b10100 )
b10100 '
#840
b10101 !
b10101 *
b101 .
14
1%
#860
12
b101 -
b10101 !
b10101 *
b101 .
14
0%
b10101 $
b10101 )
b10101 '
#880
19
17
bz001 0
13
b10110 !
b10110 *
b110 .
04
1%
#900
0B
0A
0=
1>
0<
08
07
bz000 0
03
02
19
16
b110 -
b10110 !
b10110 *
b110 .
04
0%
b10110 $
b10110 )
b10110 '
#920
b10111 !
b10111 *
b111 .
14
1%
#940
12
b111 -
b10111 !
b10111 *
b111 .
14
0%
b10111 $
b10111 )
b10111 '
#960
1B
1A
1=
0>
1<
18
09
17
bz111 0
13
b11000 !
b11000 *
b1000 .
04
1%
#980
0Q
0O
bz000 H
0K
0<
0A
b1 F
1L
0E
08
0=
bz000 +
0/
07
bz000 0
03
02
09
06
0>
0;
1B
1@
b1000 -
b11000 !
b11000 *
b1000 .
04
0%
b11000 $
b11000 )
b11000 '
#1000
b11001 !
b11001 *
b1001 .
14
1%
#1020
12
b1001 -
b11001 !
b11001 *
b1001 .
14
0%
b11001 $
b11001 )
b11001 '
#1040
19
17
bz001 0
13
b11010 !
b11010 *
b1010 .
04
1%
#1060
0>
0<
08
07
bz000 0
03
02
19
16
b1010 -
b11010 !
b11010 *
b1010 .
04
0%
b11010 $
b11010 )
b11010 '
#1080
b11011 !
b11011 *
b1011 .
14
1%
#1100
12
b1011 -
b11011 !
b11011 *
b1011 .
14
0%
b11011 $
b11011 )
b11011 '
#1120
1>
1<
18
09
17
bz011 0
13
b11100 !
b11100 *
b1100 .
04
1%
#1140
0Q
0O
bz000 H
0K
b1 F
1L
0E
bz000 +
0/
0<
1B
0A
08
0=
07
bz000 0
03
02
09
06
1>
1;
b1100 -
b11100 !
b11100 *
b1100 .
04
0%
b11100 $
b11100 )
b11100 '
#1160
b11101 !
b11101 *
b1101 .
14
1%
#1180
12
b1101 -
b11101 !
b11101 *
b1101 .
14
0%
b11101 $
b11101 )
b11101 '
#1200
19
17
bz001 0
13
b11110 !
b11110 *
b1110 .
04
1%
#1220
0Q
0O
bz000 H
0K
b1 F
1L
0E
bz000 +
0/
1B
0A
0=
1>
0<
08
07
bz000 0
03
02
19
16
b1110 -
b11110 !
b11110 *
b1110 .
04
0%
b11110 $
b11110 )
b11110 '
#1240
b11111 !
b11111 *
b1111 .
14
1%
#1260
12
b1111 -
b11111 !
b11111 *
b1111 .
14
0%
b11111 $
b11111 )
b11111 '
#1280
1Q
1O
bz001 H
1K
b10 F
0L
1E
bz001 +
1/
0B
1A
1=
0>
1<
18
09
17
bz111 0
13
b100000 !
b100000 *
b0 .
04
1%
#1300
0<
0A
0E
0O
0V
0T
08
0=
bz000 +
0/
0K
bz000 H
0P
07
bz000 0
03
02
09
06
0>
0;
0B
0@
0L
0J
b10 F
1Q
1N
b0 -
b10 D
b100000 !
b100000 *
b0 .
04
0%
b100000 $
b100000 )
b100000 '
#1320
b100001 !
b100001 *
b1 .
14
1%
#1340
12
b1 -
b100001 !
b100001 *
b1 .
14
0%
b100001 $
b100001 )
b100001 '
#1360
19
17
bz001 0
13
b100010 !
b100010 *
b10 .
04
1%
#1380
0>
0<
08
07
bz000 0
03
02
19
16
b10 -
b100010 !
b100010 *
b10 .
04
0%
b100010 $
b100010 )
b100010 '
#1400
b100011 !
b100011 *
b11 .
14
1%
#1420
12
b11 -
b100011 !
b100011 *
b11 .
14
0%
b100011 $
b100011 )
b100011 '
#1440
1>
1<
18
09
17
bz011 0
13
b100100 !
b100100 *
b100 .
04
1%
#1460
0<
0B
0A
08
0=
07
bz000 0
03
02
09
06
1>
1;
b100 -
b100100 !
b100100 *
b100 .
04
0%
b100100 $
b100100 )
b100100 '
#1480
b100101 !
b100101 *
b101 .
14
1%
#1500
12
b101 -
b100101 !
b100101 *
b101 .
14
0%
b100101 $
b100101 )
b100101 '
#1520
19
17
bz001 0
13
b100110 !
b100110 *
b110 .
04
1%
#1540
0B
0A
0=
1>
0<
08
07
bz000 0
03
02
19
16
b110 -
b100110 !
b100110 *
b110 .
04
0%
b100110 $
b100110 )
b100110 '
#1560
b100111 !
b100111 *
b111 .
14
1%
#1580
12
b111 -
b100111 !
b100111 *
b111 .
14
0%
b100111 $
b100111 )
b100111 '
#1600
1B
1A
1=
0>
1<
18
09
17
bz111 0
13
b101000 !
b101000 *
b1000 .
04
1%
#1620
0<
0A
b10 F
0L
0E
08
0=
bz000 +
0/
07
bz000 0
03
02
09
06
0>
0;
1B
1@
b1000 -
b101000 !
b101000 *
b1000 .
04
0%
b101000 $
b101000 )
b101000 '
#1640
b101001 !
b101001 *
b1001 .
14
1%
#1660
12
b1001 -
b101001 !
b101001 *
b1001 .
14
0%
b101001 $
b101001 )
b101001 '
#1680
19
17
bz001 0
13
b101010 !
b101010 *
b1010 .
04
1%
#1700
0>
0<
08
07
bz000 0
03
02
19
16
b1010 -
b101010 !
b101010 *
b1010 .
04
0%
b101010 $
b101010 )
b101010 '
#1720
b101011 !
b101011 *
b1011 .
14
1%
#1740
12
b1011 -
b101011 !
b101011 *
b1011 .
14
0%
b101011 $
b101011 )
b101011 '
#1760
1>
1<
18
09
17
bz011 0
13
b101100 !
b101100 *
b1100 .
04
1%
#1780
b10 F
0L
0E
bz000 +
0/
0<
1B
0A
08
0=
07
bz000 0
03
02
09
06
1>
1;
b1100 -
b101100 !
b101100 *
b1100 .
04
0%
b101100 $
b101100 )
b101100 '
#1800
b101101 !
b101101 *
b1101 .
14
1%
#1820
12
b1101 -
b101101 !
b101101 *
b1101 .
14
0%
b101101 $
b101101 )
b101101 '
#1840
19
17
bz001 0
13
b101110 !
b101110 *
b1110 .
04
1%
#1860
b10 F
0L
0E
bz000 +
0/
1B
0A
0=
1>
0<
08
07
bz000 0
03
02
19
16
b1110 -
b101110 !
b101110 *
b1110 .
04
0%
b101110 $
b101110 )
b101110 '
#1880
b101111 !
b101111 *
b1111 .
14
1%
#1900
12
b1111 -
b101111 !
b101111 *
b1111 .
14
0%
b101111 $
b101111 )
b101111 '
#1920
b11 F
1L
1E
bz001 +
1/
0B
1A
1=
0>
1<
18
09
17
bz111 0
13
b110000 !
b110000 *
b0 .
04
1%
#1940
0V
0T
0P
0<
0A
0E
1Q
0O
08
0=
bz000 +
0/
bz000 H
0K
07
bz000 0
03
02
09
06
0>
0;
0B
0@
b11 F
1L
1J
b0 -
b11 D
b110000 !
b110000 *
b0 .
04
0%
b110000 $
b110000 )
b110000 '
#1960
b110001 !
b110001 *
b1 .
14
1%
#1980
12
b1 -
b110001 !
b110001 *
b1 .
14
0%
b110001 $
b110001 )
b110001 '
#2000
19
17
bz001 0
13
b110010 !
b110010 *
b10 .
04
1%
#2020
0>
0<
08
07
bz000 0
03
02
19
16
b10 -
b110010 !
b110010 *
b10 .
04
0%
b110010 $
b110010 )
b110010 '
#2040
b110011 !
b110011 *
b11 .
14
1%
#2060
12
b11 -
b110011 !
b110011 *
b11 .
14
0%
b110011 $
b110011 )
b110011 '
#2080
1>
1<
18
09
17
bz011 0
13
b110100 !
b110100 *
b100 .
04
1%
#2100
0<
0B
0A
08
0=
07
bz000 0
03
02
09
06
1>
1;
b100 -
b110100 !
b110100 *
b100 .
04
0%
b110100 $
b110100 )
b110100 '
#2120
b110101 !
b110101 *
b101 .
14
1%
#2140
12
b101 -
b110101 !
b110101 *
b101 .
14
0%
b110101 $
b110101 )
b110101 '
#2160
19
17
bz001 0
13
b110110 !
b110110 *
b110 .
04
1%
#2180
0B
0A
0=
1>
0<
08
07
bz000 0
03
02
19
16
b110 -
b110110 !
b110110 *
b110 .
04
0%
b110110 $
b110110 )
b110110 '
#2200
b110111 !
b110111 *
b111 .
14
1%
#2220
12
b111 -
b110111 !
b110111 *
b111 .
14
0%
b110111 $
b110111 )
b110111 '
#2240
1B
1A
1=
0>
1<
18
09
17
bz111 0
13
b111000 !
b111000 *
b1000 .
04
1%
#2260
0V
0T
0P
1Q
0O
bz000 H
0K
0<
0A
b11 F
1L
0E
08
0=
bz000 +
0/
07
bz000 0
03
02
09
06
0>
0;
1B
1@
b1000 -
b111000 !
b111000 *
b1000 .
04
0%
b111000 $
b111000 )
b111000 '
#2280
b111001 !
b111001 *
b1001 .
14
1%
#2300
12
b1001 -
b111001 !
b111001 *
b1001 .
14
0%
b111001 $
b111001 )
b111001 '
#2320
19
17
bz001 0
13
b111010 !
b111010 *
b1010 .
04
1%
#2340
0>
0<
08
07
bz000 0
03
02
19
16
b1010 -
b111010 !
b111010 *
b1010 .
04
0%
b111010 $
b111010 )
b111010 '
#2360
b111011 !
b111011 *
b1011 .
14
1%
#2380
12
b1011 -
b111011 !
b111011 *
b1011 .
14
0%
b111011 $
b111011 )
b111011 '
#2400
1>
1<
18
09
17
bz011 0
13
b111100 !
b111100 *
b1100 .
04
1%
#2420
0V
0T
0P
1Q
0O
bz000 H
0K
b11 F
1L
0E
bz000 +
0/
0<
1B
0A
08
0=
07
bz000 0
03
02
09
06
1>
1;
b1100 -
b111100 !
b111100 *
b1100 .
04
0%
b111100 $
b111100 )
b111100 '
#2440
b111101 !
b111101 *
b1101 .
14
1%
#2460
12
b1101 -
b111101 !
b111101 *
b1101 .
14
0%
b111101 $
b111101 )
b111101 '
#2480
19
17
bz001 0
13
b111110 !
b111110 *
b1110 .
04
1%
#2500
0V
0T
0P
1Q
0O
bz000 H
0K
b11 F
1L
0E
bz000 +
0/
1B
0A
0=
1>
0<
08
07
bz000 0
03
02
19
16
b1110 -
b111110 !
b111110 *
b1110 .
04
0%
b111110 $
b111110 )
b111110 '
#2520
b111111 !
b111111 *
b1111 .
14
1%
#2540
12
b1111 -
b111111 !
b111111 *
b1111 .
14
0%
b111111 $
b111111 )
b111111 '
#2560
1V
1T
1P
0Q
1O
bz011 H
1K
b100 F
0L
1E
bz001 +
1/
0B
1A
1=
0>
1<
18
09
17
bz111 0
13
b1000000 !
b1000000 *
b0 .
04
1%
#2580
0<
0A
0E
0O
0T
0Z
0Y
08
0=
bz000 +
0/
0K
0P
bz000 H
0U
07
bz000 0
03
02
09
06
0>
0;
0B
0@
0L
0J
0Q
0N
b100 F
1V
1S
b0 -
b100 D
b1000000 !
b1000000 *
b0 .
04
0%
b1000000 $
b1000000 )
b1000000 '
#2600
b1000001 !
b1000001 *
b1 .
14
1%
#2620
12
b1 -
b1000001 !
b1000001 *
b1 .
14
0%
b1000001 $
b1000001 )
b1000001 '
#2640
19
17
bz001 0
13
b1000010 !
b1000010 *
b10 .
04
1%
#2660
0>
0<
08
07
bz000 0
03
02
19
16
b10 -
b1000010 !
b1000010 *
b10 .
04
0%
b1000010 $
b1000010 )
b1000010 '
#2680
b1000011 !
b1000011 *
b11 .
14
1%
#2700
12
b11 -
b1000011 !
b1000011 *
b11 .
14
0%
b1000011 $
b1000011 )
b1000011 '
#2720
1>
1<
18
09
17
bz011 0
13
b1000100 !
b1000100 *
b100 .
04
1%
#2740
0<
0B
0A
08
0=
07
bz000 0
03
02
09
06
1>
1;
b100 -
b1000100 !
b1000100 *
b100 .
04
0%
b1000100 $
b1000100 )
b1000100 '
#2760
b1000101 !
b1000101 *
b101 .
14
1%
#2780
12
b101 -
b1000101 !
b1000101 *
b101 .
14
0%
b1000101 $
b1000101 )
b1000101 '
#2800
19
17
bz001 0
13
b1000110 !
b1000110 *
b110 .
04
1%
#2820
0B
0A
0=
1>
0<
08
07
bz000 0
03
02
19
16
b110 -
b1000110 !
b1000110 *
b110 .
04
0%
b1000110 $
b1000110 )
b1000110 '
#2840
b1000111 !
b1000111 *
b111 .
14
1%
#2860
12
b111 -
b1000111 !
b1000111 *
b111 .
14
0%
b1000111 $
b1000111 )
b1000111 '
#2880
1B
1A
1=
0>
1<
18
09
17
bz111 0
13
b1001000 !
b1001000 *
b1000 .
04
1%
#2900
0<
0A
b100 F
0L
0E
08
0=
bz000 +
0/
07
bz000 0
03
02
09
06
0>
0;
1B
1@
b1000 -
b1001000 !
b1001000 *
b1000 .
04
0%
b1001000 $
b1001000 )
b1001000 '
#2920
b1001001 !
b1001001 *
b1001 .
14
1%
#2940
12
b1001 -
b1001001 !
b1001001 *
b1001 .
14
0%
b1001001 $
b1001001 )
b1001001 '
#2960
19
17
bz001 0
13
b1001010 !
b1001010 *
b1010 .
04
1%
#2980
0>
0<
08
07
bz000 0
03
02
19
16
b1010 -
b1001010 !
b1001010 *
b1010 .
04
0%
b1001010 $
b1001010 )
b1001010 '
#3000
b1001011 !
b1001011 *
b1011 .
14
1%
#3020
12
b1011 -
b1001011 !
b1001011 *
b1011 .
14
0%
b1001011 $
b1001011 )
b1001011 '
#3040
1>
1<
18
09
17
bz011 0
13
b1001100 !
b1001100 *
b1100 .
04
1%
#3060
b100 F
0L
0E
bz000 +
0/
0<
1B
0A
08
0=
07
bz000 0
03
02
09
06
1>
1;
b1100 -
b1001100 !
b1001100 *
b1100 .
04
0%
b1001100 $
b1001100 )
b1001100 '
#3080
b1001101 !
b1001101 *
b1101 .
14
1%
#3100
12
b1101 -
b1001101 !
b1001101 *
b1101 .
14
0%
b1001101 $
b1001101 )
b1001101 '
#3120
19
17
bz001 0
13
b1001110 !
b1001110 *
b1110 .
04
1%
#3140
b100 F
0L
0E
bz000 +
0/
1B
0A
0=
1>
0<
08
07
bz000 0
03
02
19
16
b1110 -
b1001110 !
b1001110 *
b1110 .
04
0%
b1001110 $
b1001110 )
b1001110 '
#3160
b1001111 !
b1001111 *
b1111 .
14
1%
#3180
12
b1111 -
b1001111 !
b1001111 *
b1111 .
14
0%
b1001111 $
b1001111 )
b1001111 '
#3200
b101 F
1L
1E
bz001 +
1/
0B
1A
1=
0>
1<
18
09
17
bz111 0
13
b1010000 !
b1010000 *
b0 .
04
1%
#3220
0<
0A
0E
0Q
0O
08
0=
bz000 +
0/
bz000 H
0K
07
bz000 0
03
02
09
06
0>
0;
0B
0@
b101 F
1L
1J
b0 -
b101 D
b1010000 !
b1010000 *
b0 .
04
0%
b1010000 $
b1010000 )
b1010000 '
#3240
b1010001 !
b1010001 *
b1 .
14
1%
#3260
12
b1 -
b1010001 !
b1010001 *
b1 .
14
0%
b1010001 $
b1010001 )
b1010001 '
#3280
19
17
bz001 0
13
b1010010 !
b1010010 *
b10 .
04
1%
#3300
0>
0<
08
07
bz000 0
03
02
19
16
b10 -
b1010010 !
b1010010 *
b10 .
04
0%
b1010010 $
b1010010 )
b1010010 '
#3320
b1010011 !
b1010011 *
b11 .
14
1%
#3340
12
b11 -
b1010011 !
b1010011 *
b11 .
14
0%
b1010011 $
b1010011 )
b1010011 '
#3360
1>
1<
18
09
17
bz011 0
13
b1010100 !
b1010100 *
b100 .
04
1%
#3380
0<
0B
0A
08
0=
07
bz000 0
03
02
09
06
1>
1;
b100 -
b1010100 !
b1010100 *
b100 .
04
0%
b1010100 $
b1010100 )
b1010100 '
#3400
b1010101 !
b1010101 *
b101 .
14
1%
#3420
12
b101 -
b1010101 !
b1010101 *
b101 .
14
0%
b1010101 $
b1010101 )
b1010101 '
#3440
19
17
bz001 0
13
b1010110 !
b1010110 *
b110 .
04
1%
#3460
0B
0A
0=
1>
0<
08
07
bz000 0
03
02
19
16
b110 -
b1010110 !
b1010110 *
b110 .
04
0%
b1010110 $
b1010110 )
b1010110 '
#3480
b1010111 !
b1010111 *
b111 .
14
1%
#3500
12
b111 -
b1010111 !
b1010111 *
b111 .
14
0%
b1010111 $
b1010111 )
b1010111 '
#3520
1B
1A
1=
0>
1<
18
09
17
bz111 0
13
b1011000 !
b1011000 *
b1000 .
04
1%
#3540
0Q
0O
bz000 H
0K
0<
0A
b101 F
1L
0E
08
0=
bz000 +
0/
07
bz000 0
03
02
09
06
0>
0;
1B
1@
b1000 -
b1011000 !
b1011000 *
b1000 .
04
0%
b1011000 $
b1011000 )
b1011000 '
#3560
b1011001 !
b1011001 *
b1001 .
14
1%
#3580
12
b1001 -
b1011001 !
b1011001 *
b1001 .
14
0%
b1011001 $
b1011001 )
b1011001 '
#3600
19
17
bz001 0
13
b1011010 !
b1011010 *
b1010 .
04
1%
#3620
0>
0<
08
07
bz000 0
03
02
19
16
b1010 -
b1011010 !
b1011010 *
b1010 .
04
0%
b1011010 $
b1011010 )
b1011010 '
#3640
b1011011 !
b1011011 *
b1011 .
14
1%
#3660
12
b1011 -
b1011011 !
b1011011 *
b1011 .
14
0%
b1011011 $
b1011011 )
b1011011 '
#3680
1>
1<
18
09
17
bz011 0
13
b1011100 !
b1011100 *
b1100 .
04
1%
#3700
0Q
0O
bz000 H
0K
b101 F
1L
0E
bz000 +
0/
0<
1B
0A
08
0=
07
bz000 0
03
02
09
06
1>
1;
b1100 -
b1011100 !
b1011100 *
b1100 .
04
0%
b1011100 $
b1011100 )
b1011100 '
#3720
b1011101 !
b1011101 *
b1101 .
14
1%
#3740
12
b1101 -
b1011101 !
b1011101 *
b1101 .
14
0%
b1011101 $
b1011101 )
b1011101 '
#3760
19
17
bz001 0
13
b1011110 !
b1011110 *
b1110 .
04
1%
#3780
0Q
0O
bz000 H
0K
b101 F
1L
0E
bz000 +
0/
1B
0A
0=
1>
0<
08
07
bz000 0
03
02
19
16
b1110 -
b1011110 !
b1011110 *
b1110 .
04
0%
b1011110 $
b1011110 )
b1011110 '
#3800
b1011111 !
b1011111 *
b1111 .
14
1%
#3820
12
b1111 -
b1011111 !
b1011111 *
b1111 .
14
0%
b1011111 $
b1011111 )
b1011111 '
#3840
1Q
1O
bz001 H
1K
b110 F
0L
1E
bz001 +
1/
0B
1A
1=
0>
1<
18
09
17
bz111 0
13
b1100000 !
b1100000 *
b0 .
04
1%
