components/adder/adder.v
// Created by Kavan Heppenstall, 22/08/2024

module adder1bit(A, B, C_in, S, C_out);

input A, B, C_in;
output S, C_out;

assign S = A + B + C_in;

assign C_out = (A & B) | (A & C_in) | (B & C_in);

endmodule

module adder4bit(A, B, C_in, S, C_out);

input [3:0] A, B;
input C_in;

output [3:0] S;
output C_out;

wire [3:0] C_internal;

adder1bit A0(.A(A[0]), .B(B[0]), .C_in(C_in), .S(S[0]), .C_out(C_internal[0]));

adder1bit A1(.A(A[1]), .B(B[1]), .C_in(C_internal[0]), .S(S[1]), .C_out(C_internal[1]));

adder1bit A2(.A(A[2]), .B(B[2]), .C_in(C_internal[1]), .S(S[2]), .C_out(C_internal[2]));

adder1bit A3(.A(A[3]), .B(B[3]), .C_in(C_internal[2]), .S(S[3]), .C_out(C_out));


endmodule

module adder16bit(A, B, C_in, S, C_out);

    input [15:0] A, B;
    input C_in;

    output [15:0] S;
    output C_out;

    wire [3:0] C_internal;

    adder4bit A0(.A(A[3:0]), .B(B[3:0]), .C_in(C_in), .S(S[3:0]), .C_out(C_internal[0]));
    
    adder4bit A1(.A(A[7:4]), .B(B[7:4]), .C_in(C_internal[0]), .S(S[7:4]), .C_out(C_internal[1]));
    
    adder4bit A2(.A(A[11:8]), .B(B[11:8]), .C_in(C_internal[1]), .S(S[11:8]), .C_out(C_internal[2]));
    
    adder4bit A3(.A(A[15:12]), .B(B[15:12]), .C_in(C_internal[2]), .S(S[15:12]), .C_out(C_out));


endmodule

components/adder/adder4bit_tb.v
`timescale 1ns/1ns
`include "adder.v"

module adder4bit_tb;

reg [3:0] A, B;
reg C_in;

wire [3:0] S;
wire C_out;

integer i, j;

adder4bit dut(A, B, C_in, S, C_out);

initial begin
    
    $dumpfile("adder4bit_tb.vcd");
    $dumpvars(0, adder4bit_tb);

    #20;

    for (i = 0; i < 16; i = i + 1) begin
        
        for (j = 0; j < 16; j = j + 1) begin
            
            A = i; B = j; C_in = 1'b0; #20;
            
            A = i; B = j; C_in = 1'b1; #20;

        end

    end


    $display("end");

end


endmodule

components/adder/adder4bit_tb.vcd
$date
	Thu Aug 22 14:28:30 2024
$end
$version
	Icarus Verilog
$end
$timescale
	1ns
$end
$scope module adder4bit_tb $end
$var wire 4 ! S [3:0] $end
$var wire 1 " C_out $end
$var reg 4 # A [3:0] $end
$var reg 4 $ B [3:0] $end
$var reg 1 % C_in $end
$var integer 32 & i [31:0] $end
$var integer 32 ' j [31:0] $end
$scope module dut $end
$var wire 4 ( A [3:0] $end
$var wire 4 ) B [3:0] $end
$var wire 1 % C_in $end
$var wire 4 * S [3:0] $end
$var wire 1 " C_out $end
$var wire 4 + C_internal [3:0] $end
$scope module A0 $end
$var wire 1 , A $end
$var wire 1 - B $end
$var wire 1 % C_in $end
$var wire 1 . C_out $end
$var wire 1 / S $end
$upscope $end
$scope module A1 $end
$var wire 1 0 A $end
$var wire 1 1 B $end
$var wire 1 2 C_in $end
$var wire 1 3 C_out $end
$var wire 1 4 S $end
$upscope $end
$scope module A2 $end
$var wire 1 5 A $end
$var wire 1 6 B $end
$var wire 1 7 C_in $end
$var wire 1 8 C_out $end
$var wire 1 9 S $end
$upscope $end
$scope module A3 $end
$var wire 1 : A $end
$var wire 1 ; B $end
$var wire 1 < C_in $end
$var wire 1 " C_out $end
$var wire 1 = S $end
$upscope $end
$upscope $end
$upscope $end
$enddefinitions $end
$comment Show the parameter values. $end
$dumpall
$end
#0
$dumpvars
x=
x<
x;
x:
x9
x8
x7
x6
x5
x4
x3
x2
x1
x0
x/
x.
x-
x,
bzxxx +
bx *
bx )
bx (
bx '
bx &
x%
bx $
bx #
x"
bx !
$end
#20
04
02
09
07
0=
0<
0.
03
bz000 +
08
0"
b0 !
b0 *
0/
0-
01
06
0;
0,
00
05
0:
0%
b0 $
b0 )
b0 #
b0 (
b0 '
b0 &
#40
b1 !
b1 *
1/
1%
#60
1-
b1 !
b1 *
1/
0%
b1 $
b1 )
b1 '
#80
14
12
bz001 +
1.
b10 !
b10 *
0/
1%
#100
09
07
02
03
bz000 +
0.
0-
14
11
b10 !
b10 *
0/
0%
b10 $
b10 )
b10 '
#120
b11 !
b11 *
1/
1%
#140
1-
b11 !
b11 *
1/
0%
b11 $
b11 )
b11 '
#160
19
17
13
04
12
bz011 +
1.
b100 !
b100 *
0/
1%
#180
07
0=
0<
02
03
08
bz000 +
0.
0-
04
01
19
16
b100 !
b100 *
0/
0%
b100 $
b100 )
b100 '
#200
b101 !
b101 *
1/
1%
#220
1-
b101 !
b101 *
1/
0%
b101 $
b101 )
b101 '
#240
14
12
bz001 +
1.
b110 !
b110 *
0/
1%
#260
0=
0<
08
19
07
02
03
bz000 +
0.
0-
14
11
b110 !
b110 *
0/
0%
b110 $
b110 )
b110 '
#280
b111 !
b111 *
1/
1%
#300
1-
b111 !
b111 *
1/
0%
b111 $
b111 )
b111 '
#320
1=
1<
18
09
17
13
04
12
bz111 +
1.
b1000 !
b1000 *
0/
1%
#340
07
0<
02
03
08
0"
bz000 +
0.
0-
04
01
09
06
1=
1;
b1000 !
b1000 *
0/
0%
b1000 $
b1000 )
b1000 '
#360
b1001 !
b1001 *
1/
1%
#380
1-
b1001 !
b1001 *
1/
0%
b1001 $
b1001 )
b1001 '
#400
14
12
bz001 +
1.
b1010 !
b1010 *
0/
1%
#420
09
07
02
03
bz000 +
0.
0-
14
11
b1010 !
b1010 *
0/
0%
b1010 $
b1010 )
b1010 '
#440
b1011 !
b1011 *
1/
1%
#460
1-
b1011 !
b1011 *
1/
0%
b1011 $
b1011 )
b1011 '
#480
19
17
13
04
12
bz011 +
1.
b1100 !
b1100 *
0/
1%
#500
0"
07
1=
0<
02
03
08
bz000 +
0.
0-
04
01
19
16
b1100 !
b1100 *
0/
0%
b1100 $
b1100 )
b1100 '
#520
b1101 !
b1101 *
1/
1%
#540
1-
b1101 !
b1101 *
1/
0%
b1101 $
b1101 )
b1101 '
#560
14
12
bz001 +
1.
b1110 !
b1110 *
0/
1%
#580
0"
1=
0<
08
19
07
02
03
bz000 +
0.
0-
14
11
b1110 !
b1110 *
0/
0%
b1110 $
b1110 )
b1110 '
#600
b1111 !
b1111 *
1/
1%
#620
1-
b1111 !
b1111 *
1/
0%
b1111 $
b1111 )
b1111 '
#640
1"
0=
1<
18
09
17
13
04
12
bz111 +
1.
b0 !
b0 *
0/
1%
#660
07
0<
02
03
08
0"
bz000 +
0.
0-
04
01
09
06
0=
0;
1,
b1 !
b1 *
1/
0%
b0 $
b0 )
b1 #
b1 (
b1 &
b0 '
#680
14
12
bz001 +
1.
b10 !
b10 *
0/
1%
#700
1-
b10 !
b10 *
0/
0%
b1 $
b1 )
b1 '
#720
b11 !
b11 *
1/
1%
#740
02
09
07
0.
bz000 +
03
0-
14
11
b11 !
b11 *
1/
0%
b10 $
b10 )
b10 '
#760
19
17
13
04
12
bz011 +
1.
b100 !
b100 *
0/
1%
#780
1-
b100 !
b100 *
0/
0%
b11 $
b11 )
b11 '
#800
b101 !
b101 *
1/
1%
#820
02
07
0=
0<
0.
03
bz000 +
08
0-
04
01
19
16
b101 !
b101 *
1/
0%
b100 $
b100 )
b100 '
#840
14
12
bz001 +
1.
b110 !
b110 *
0/
1%
#860
1-
b110 !
b110 *
0/
0%
b101 $
b101 )
b101 '
#880
b111 !
b111 *
1/
1%
#900
0=
0<
08
02
19
07
0.
bz000 +
03
0-
14
11
b111 !
b111 *
1/
0%
b110 $
b110 )
b110 '
#920
1=
1<
18
09
17
13
04
12
bz111 +
1.
b1000 !
b1000 *
0/
1%
#940
1-
b1000 !
b1000 *
0/
0%
b111 $
b111 )
b111 '
#960
b1001 !
b1001 *
1/
1%
#980
02
07
0<
0.
03
bz000 +
08
0"
0-
04
01
09
06
1=
1;
b1001 !
b1001 *
1/
0%
b1000 $
b1000 )
b1000 '
#1000
14
12
bz001 +
1.
b1010 !
b1010 *
0/
1%
#1020
1-
b1010 !
b1010 *
0/
0%
b1001 $
b1001 )
b1001 '
#1040
b1011 !
b1011 *
1/
1%
#1060
02
09
07
0.
bz000 +
03
0-
14
11
b1011 !
b1011 *
1/
0%
b1010 $
b1010 )
b1010 '
#1080
19
17
13
04
12
bz011 +
1.
b1100 !
b1100 *
0/
1%
#1100
1-
b1100 !
b1100 *
0/
0%
b1011 $
b1011 )
b1011 '
#1120
b1101 !
b1101 *
1/
1%
#1140
0"
02
07
1=
0<
0.
03
bz000 +
08
0-
04
01
19
16
b1101 !
b1101 *
1/
0%
b1100 $
b1100 )
b1100 '
#1160
14
12
bz001 +
1.
b1110 !
b1110 *
0/
1%
#1180
1-
b1110 !
b1110 *
0/
0%
b1101 $
b1101 )
b1101 '
#1200
b1111 !
b1111 *
1/
1%
#1220
0"
1=
0<
08
02
19
07
0.
bz000 +
03
0-
14
11
b1111 !
b1111 *
1/
0%
b1110 $
b1110 )
b1110 '
#1240
1"
0=
1<
18
09
17
13
04
12
bz111 +
1.
b0 !
b0 *
0/
1%
#1260
1-
b0 !
b0 *
0/
0%
b1111 $
b1111 )
b1111 '
#1280
b1 !
b1 *
1/
1%
#1300
07
03
02
0<
0.
bz000 +
08
0"
0-
01
09
06
0=
0;
0,
14
10
b10 !
b10 *
0/
0%
b0 $
b0 )
b10 #
b10 (
b10 &
b0 '
#1320
b11 !
b11 *
1/
1%
#1340
1-
b11 !
b11 *
1/
0%
b1 $
b1 )
b1 '
#1360
19
17
13
04
12
bz011 +
1.
b100 !
b100 *
0/
1%
#1380
02
bz010 +
0.
0-
04
11
b100 !
b100 *
0/
0%
b10 $
b10 )
b10 '
#1400
b101 !
b101 *
1/
1%
#1420
1-
b101 !
b101 *
1/
0%
b11 $
b11 )
b11 '
#1440
14
12
bz011 +
1.
b110 !
b110 *
0/
1%
#1460
07
03
0=
0<
02
08
bz000 +
0.
0-
14
01
19
16
b110 !
b110 *
0/
0%
b100 $
b100 )
b100 '
#1480
b111 !
b111 *
1/
1%
#1500
1-
b111 !
b111 *
1/
0%
b101 $
b101 )
b101 '
#1520
1=
1<
18
09
17
13
04
12
bz111 +
1.
b1000 !
b1000 *
0/
1%
#1540
02
bz110 +
0.
0-
04
11
b1000 !
b1000 *
0/
0%
b110 $
b110 )
b110 '
#1560
b1001 !
b1001 *
1/
1%
#1580
1-
b1001 !
b1001 *
1/
0%
b111 $
b111 )
b111 '
#1600
14
12
bz111 +
1.
b1010 !
b1010 *
0/
1%
#1620
07
03
0<
02
08
0"
bz000 +
0.
0-
14
01
09
06
1=
1;
b1010 !
b1010 *
0/
0%
b1000 $
b1000 )
b1000 '
#1640
b1011 !
b1011 *
1/
1%
#1660
1-
b1011 !
b1011 *
1/
0%
b1001 $
b1001 )
b1001 '
#1680
19
17
13
04
12
bz011 +
1.
b1100 !
b1100 *
0/
1%
#1700
02
bz010 +
0.
0-
04
11
b1100 !
b1100 *
0/
0%
b1010 $
b1010 )
b1010 '
#1720
b1101 !
b1101 *
1/
1%
#1740
1-
b1101 !
b1101 *
1/
0%
b1011 $
b1011 )
b1011 '
#1760
14
12
bz011 +
1.
b1110 !
b1110 *
0/
1%
#1780
07
03
0"
1=
0<
02
08
bz000 +
0.
0-
14
01
19
16
b1110 !
b1110 *
0/
0%
b1100 $
b1100 )
b1100 '
#1800
b1111 !
b1111 *
1/
1%
#1820
1-
b1111 !
b1111 *
1/
0%
b1101 $
b1101 )
b1101 '
#1840
1"
0=
1<
18
09
17
13
04
12
bz111 +
1.
b0 !
b0 *
0/
1%
#1860
02
bz110 +
0.
0-
04
11
b0 !
b0 *
0/
0%
b1110 $
b1110 )
b1110 '
#1880
b1 !
b1 *
1/
1%
#1900
1-
b1 !
b1 *
1/
0%
b1111 $
b1111 )
b1111 '
#1920
14
12
bz111 +
1.
b10 !
b10 *
0/
1%
#1940
07
03
0<
02
08
0"
bz000 +
0.
0-
14
01
09
06
0=
0;
1,
b11 !
b11 *
1/
0%
b0 $
b0 )
b11 #
b11 (
b11 &
b0 '
#1960
19
17
13
04
12
bz011 +
1.
b100 !
b100 *
0/
1%
#1980
1-
b100 !
b100 *
0/
0%
b1 $
b1 )
b1 '
#2000
b101 !
b101 *
1/
1%
#2020
02
bz010 +
0.
0-
04
11
b101 !
b101 *
1/
0%
b10 $
b10 )
b10 '
#2040
14
12
bz011 +
1.
b110 !
b110 *
0/
1%
#2060
1-
b110 !
b110 *
0/
0%
b11 $
b11 )
b11 '
#2080
b111 !
b111 *
1/
1%
#2100
07
03
02
0=
0<
0.
bz000 +
08
0-
14
01
19
16
b111 !
b111 *
1/
0%
b100 $
b100 )
b100 '
#2120
1=
1<
18
09
17
13
04
12
bz111 +
1.
b1000 !
b1000 *
0/
1%
#2140
1-
b1000 !
b1000 *
0/
0%
b101 $
b101 )
b101 '
#2160
b1001 !
b1001 *
1/
1%
#2180
02
bz110 +
0.
0-
04
11
b1001 !
b1001 *
1/
0%
b110 $
b110 )
b110 '
#2200
14
12
bz111 +
1.
b1010 !
b1010 *
0/
1%
#2220
1-
b1010 !
b1010 *
0/
0%
b111 $
b111 )
b111 '
#2240
b1011 !
b1011 *
1/
1%
#2260
07
03
02
0<
0.
bz000 +
08
0"
0-
14
01
09
06
1=
1;
b1011 !
b1011 *
1/
0%
b1000 $
b1000 )
b1000 '
#2280
19
17
13
04
12
bz011 +
1.
b1100 !
b1100 *
0/
1%
#2300
1-
b1100 !
b1100 *
0/
0%
b1001 $
b1001 )
b1001 '
#2320
b1101 !
b1101 *
1/
1%
#2340
02
bz010 +
0.
0-
04
11
b1101 !
b1101 *
1/
0%
b1010 $
b1010 )
b1010 '
#2360
14
12
bz011 +
1.
b1110 !
b1110 *
0/
1%
#2380
1-
b1110 !
b1110 *
0/
0%
b1011 $
b1011 )
b1011 '
#2400
b1111 !
b1111 *
1/
1%
#2420
07
03
0"
02
1=
0<
0.
bz000 +
08
0-
14
01
19
16
b1111 !
b1111 *
1/
0%
b1100 $
b1100 )
b1100 '
#2440
1"
0=
1<
18
09
17
13
04
12
bz111 +
1.
b0 !
b0 *
0/
1%
#2460
1-
b0 !
b0 *
0/
0%
b1101 $
b1101 )
b1101 '
#2480
b1 !
b1 *
1/
1%
#2500
02
bz110 +
0.
0-
04
11
b1 !
b1 *
1/
0%
b1110 $
b1110 )
b1110 '
#2520
14
12
bz111 +
1.
b10 !
b10 *
0/
1%
#2540
1-
b10 !
b10 *
0/
0%
b1111 $
b1111 )
b1111 '
#2560
b11 !
b11 *
1/
1%
#2580
0<
08
02
07
0.
bz000 +
03
0"
0-
01
06
0=
0;
0,
04
00
19
15
b100 !
b100 *
0/
0%
b0 $
b0 )
b100 #
b100 (
b100 &
b0 '
#2600
b101 !
b101 *
1/
1%
#2620
1-
b101 !
b101 *
1/
0%
b1 $
b1 )
b1 '
#2640
14
12
bz001 +
1.
b110 !
b110 *
0/
1%
#2660
0=
0<
08
19
07
02
03
bz000 +
0.
0-
14
11
b110 !
b110 *
0/
0%
b10 $
b10 )
b10 '
#2680
b111 !
b111 *
1/
1%
#2700
1-
b111 !
b111 *
1/
0%
b11 $
b11 )
b11 '
#2720
1=
1<
18
09
17
13
04
12
bz111 +
1.
b1000 !
b1000 *
0/
1%
#2740
07
02
03
bz100 +
0.
0-
04
01
09
16
b1000 !
b1000 *
0/
0%
b100 $
b100 )
b100 '
#2760
b1001 !
b1001 *
1/
1%
#2780
1-
b1001 !
b1001 *
1/
0%
b101 $
b101 )
b101 '
#2800
14
12
bz101 +
1.
b1010 !
b1010 *
0/
1%
#2820
09
07
02
03
bz100 +
0.
0-
14
11
b1010 !
b1010 *
0/
0%
b110 $
b110 )
b110 '
#2840
b1011 !
b1011 *
1/
1%
#2860
1-
b1011 !
b1011 *
1/
0%
b111 $
b111 )
b111 '
#2880
19
17
13
04
12
bz111 +
1.
b1100 !
b1100 *
0/
1%
#2900
0<
08
07
02
03
0"
bz000 +
0.
0-
04
01
19
06
1=
1;
b1100 !
b1100 *
0/
0%
b1000 $
b1000 )
b1000 '
#2920
b1101 !
b1101 *
1/
1%
#2940
1-
b1101 !
b1101 *
1/
0%
b1001 $
b1001 )
b1001 '
#2960
14
12
bz001 +
1.
b1110 !
b1110 *
0/
1%
#2980
0"
1=
0<
08
19
07
02
03
bz000 +
0.
0-
14
11
b1110 !
b1110 *
0/
0%
b1010 $
b1010 )
b1010 '
#3000
b1111 !
b1111 *
1/
1%
#3020
1-
b1111 !
b1111 *
1/
0%
b1011 $
b1011 )
b1011 '
#3040
1"
0=
1<
18
09
17
13
04
12
bz111 +
1.
b0 !
b0 *
0/
1%
#3060
07
02
03
bz100 +
0.
0-
04
01
09
16
b0 !
b0 *
0/
0%
b1100 $
b1100 )
b1100 '
#3080
b1 !
b1 *
1/
1%
#3100
1-
b1 !
b1 *
1/
0%
b1101 $
b1101 )
b1101 '
#3120
14
12
bz101 +
1.
b10 !
b10 *
0/
1%
#3140
09
07
02
03
bz100 +
0.
0-
14
11
b10 !
b10 *
0/
0%
b1110 $
b1110 )
b1110 '
#3160
b11 !
b11 *
1/
1%
#3180
1-
b11 !
b11 *
1/
0%
b1111 $
b1111 )
b1111 '
#3200
19
17
13
04
12
bz111 +
1.
b100 !
b100 *
0/
1%
#3220
0<
08
07
02
03
0"
bz000 +
0.
0-
04
01
19
06
0=
0;
1,
b101 !
b101 *
1/
0%
b0 $
b0 )
b101 #
b101 (
b101 &
b0 '
#3240
14
12
bz001 +
1.
b110 !
b110 *
0/
1%
#3260
1-
b110 !
b110 *
0/
0%
b1 $
b1 )
b1 '
#3280
b111 !
b111 *
1/
1%
#3300
0=
0<
08
02
19
07
0.
bz000 +
03
0-
14
11
b111 !
b111 *
1/
0%
b10 $
b10 )
b10 '
#3320
1=
1<
18
09
17
13
04
12
bz111 +
1.
b1000 !
b1000 *
0/
1%
#3340
1-
b1000 !
b1000 *
0/
0%
b11 $
b11 )
b11 '
#3360
b1001 !
b1001 *
1/
1%
#3380
02
07
0.
bz100 +
03
0-
04
01
09
16
b1001 !
b1001 *
1/
0%
b100 $
b100 )
b100 '
#3400
14
12
bz101 +
1.
b1010 !
b1010 *
0/
1%
#3420
1-
b1010 !
b1010 *
0/
0%
b101 $
b101 )
b101 '
#3440
b1011 !
b1011 *
1/
1%
#3460
02
09
07
0.
bz100 +
03
0-
14
11
b1011 !
b1011 *
1/
0%
b110 $
b110 )
b110 '
#3480
19
17
13
04
12
bz111 +
1.
b1100 !
b1100 *
0/
1%
#3500
1-
b1100 !
b1100 *
0/
0%
b111 $
b111 )
b111 '
#3520
b1101 !
b1101 *
1/
1%
#3540
0<
08
02
07
0.
bz000 +
03
0"
0-
04
01
19
06
1=
1;
b1101 !
b1101 *
1/
0%
b1000 $
b1000 )
b1000 '
#3560
14
12
bz001 +
1.
b1110 !
b1110 *
0/
1%
#3580
1-
b1110 !
b1110 *
0/
0%
b1001 $
b1001 )
b1001 '
#3600
b1111 !
b1111 *
1/
1%
#3620
0"
1=
0<
08
02
19
07
0.
bz000 +
03
0-
14
11
b1111 !
b1111 *
1/
0%
b1010 $
b1010 )
b1010 '
#3640
1"
0=
1<
18
09
17
13
04
12
bz111 +
1.
b0 !
b0 *
0/
1%
#3660
1-
b0 !
b0 *
0/
0%
b1011 $
b1011 )
b1011 '
#3680
b1 !
b1 *
1/
1%
#3700
02
07
0.
bz100 +
03
0-
04
01
09
16
b1 !
b1 *
1/
0%
b1100 $
b1100 )
b1100 '
#3720
14
12
bz101 +
1.
b10 !
b10 *
0/
1%
#3740
1-
b10 !
b10 *
0/
0%
b1101 $
b1101 )
b1101 '
#3760
b11 !
b11 *
1/
1%
#3780
02
09
07
0.
bz100 +
03
0-
14
11
b11 !
b11 *
1/
0%
b1110 $
b1110 )
b1110 '
#3800
19
17
13
04
12
bz111 +
1.
b100 !
b100 *
0/
1%
#3820
1-
b100 !
b100 *
0/
0%
b1111 $
b1111 )
b1111 '
#3840
b101 !
b101 *
1/
1%
#3860
0<
08
07
03
02
bz000 +
0.
0"
0-
01
19
06
0=
0;
0,
14
10
b110 !
b110 *
0/
0%
b0 $
b0 )
b110 #
b110 (
b110 &
b0 '
#3880
b111 !
b111 *
1/
1%
#3900
1-
b111 !
b111 *
1/
0%
b1 $
b1 )
b1 '
#3920
1=
1<
18
09
17
13
04
12
bz111 +
1.
b1000 !
b1000 *
0/
1%
#3940
02
bz110 +
0.
0-
04
11
b1000 !
b1000 *
0/
0%
b10 $
b10 )
b10 '
#3960
b1001 !
b1001 *
1/
1%
#3980
1-
b1001 !
b1001 *
1/
0%
b11 $
b11 )
b11 '
#4000
14
12
bz111 +
1.
b1010 !
b1010 *
0/
1%
#4020
07
03
02
bz100 +
0.
0-
14
01
09
16
b1010 !
b1010 *
0/
0%
b100 $
b100 )
b100 '
#4040
b1011 !
b1011 *
1/
1%
#4060
1-
b1011 !
b1011 *
1/
0%
b101 $
b101 )
b101 '
#4080
19
17
13
04
12
bz111 +
1.
b1100 !
b1100 *
0/
1%
#4100
02
bz110 +
0.
0-
04
11
b1100 !
b1100 *
0/
0%
b110 $
b110 )
b110 '
#4120
b1101 !
b1101 *
1/
1%
#4140
1-
b1101 !
b1101 *
1/
0%
b111 $
b111 )
b111 '
#4160
14
12
bz111 +
1.
b1110 !
b1110 *
0/
1%
#4180
0<
08
07
03
02
0"
bz000 +
0.
0-
14
01
19
06
1=
1;
b1110 !
b1110 *
0/
0%
b1000 $
b1000 )
b1000 '
#4200
b1111 !
b1111 *
1/
1%
#4220
1-
b1111 !
b1111 *
1/
0%
b1001 $
b1001 )
b1001 '
#4240
1"
0=
1<
18
09
17
13
04
12
bz111 +
1.
b0 !
b0 *
0/
1%
#4260
02
bz110 +
0.
0-
04
11
b0 !
b0 *
0/
0%
b1010 $
b1010 )
b1010 '
#4280
b1 !
b1 *
1/
1%
#4300
1-
b1 !
b1 *
1/
0%
b1011 $
b1011 )
b1011 '
#4320
14
12
bz111 +
1.
b10 !
b10 *
0/
1%
#4340
07
03
02
bz100 +
0.
0-
14
01
09
16
b10 !
b10 *
0/
0%
b1100 $
b1100 )
b1100 '
#4360
b11 !
b11 *
1/
1%
#4380
1-
b11 !
b11 *
1/
0%
b1101 $
b1101 )
b1101 '
#4400
19
17
13
04
12
bz111 +
1.
b100 !
b100 *
0/
1%
#4420
02
bz110 +
0.
0-
04
11
b100 !
b100 *
0/
0%
b1110 $
b1110 )
b1110 '
#4440
b101 !
b101 *
1/
1%
#4460
1-
b101 !
b101 *
1/
0%
b1111 $
b1111 )
b1111 '
#4480
14
12
bz111 +
1.
b110 !
b110 *
0/
1%
#4500
0<
08
07
03
02
0"
bz000 +
0.
0-
14
01
19
06
0=
0;
1,
b111 !
b111 *
1/
0%
b0 $
b0 )
b111 #
b111 (
b111 &
b0 '
#4520
1=
1<
18
09
17
13
04
12
bz111 +
1.
b1000 !
b1000 *
0/
1%
#4540
1-
b1000 !
b1000 *
0/
0%
b1 $
b1 )
b1 '
#4560
b1001 !
b1001 *
1/
1%
#4580
02
bz110 +
0.
0-
04
11
b1001 !
b1001 *
1/
0%
b10 $
b10 )
b10 '
#4600
14
12
bz111 +
1.
b1010 !
b1010 *
0/
1%
#4620
1-
b1010 !
b1010 *
0/
0%
b11 $
b11 )
b11 '
#4640
b1011 !
b1011 *
1/
1%
#4660
07
03
02
bz100 +
0.
0-
14
01
09
16
b1011 !
b1011 *
1/
0%
b100 $
b100 )
b100 '
#4680
19
17
13
04
12
bz111 +
1.
b1100 !
b1100 *
0/
1%
#4700
1-
b1100 !
b1100 *
0/
0%
b101 $
b101 )
b101 '
#4720
b1101 !
b1101 *
1/
1%
#4740
02
bz110 +
0.
0-
04
11
b1101 !
b1101 *
1/
0%
b110 $
b110 )
b110 '
#4760
14
12
bz111 +
1.
b1110 !
b1110 *
0/
1%
#4780
1-
b1110 !
b1110 *
0/
0%
b111 $
b111 )
b111 '
#4800
b1111 !
b1111 *
1/
1%
#4820
0<
08
07
03
02
bz000 +
0.
0"
0-
14
01
19
06
1=
1;
b1111 !
b1111 *
1/
0%
b1000 $
b1000 )
b1000 '
#4840
1"
0=
1<
18
09
17
13
04
12
bz111 +
1.
b0 !
b0 *
0/
1%
#4860
1-
b0 !
b0 *
0/
0%
b1001 $
b1001 )
b1001 '
#4880
b1 !
b1 *
1/
1%
#4900
02
bz110 +
0.
0-
04
11
b1 !
b1 *
1/
0%
b1010 $
b1010 )
b1010 '
#4920
14
12
bz111 +
1.
b10 !
b10 *
0/
1%
#4940
1-
b10 !
b10 *
0/
0%
b1011 $
b1011 )
b1011 '
#4960
b11 !
b11 *
1/
1%
#4980
07
03
02
bz100 +
0.
0-
14
01
09
16
b11 !
b11 *
1/
0%
b1100 $
b1100 )
b1100 '
#5000
19
17
13
04
12
bz111 +
1.
b100 !
b100 *
0/
1%
#5020
1-
b100 !
b100 *
0/
0%
b1101 $
b1101 )
b1101 '
#5040
b101 !
b101 *
1/
1%
#5060
02
bz110 +
0.
0-
04
11
b101 !
b101 *
1/
0%
b1110 $
b1110 )
b1110 '
#5080
14
12
bz111 +
1.
b110 !
b110 *
0/
1%
#5100
1-
b110 !
b110 *
0/
0%
b1111 $
b1111 )
b1111 '
#5120
b111 !
b111 *
1/
1%
#5140
0"
02
07
0<
0.
03
bz000 +
08
0-
01
06
0;
0,
04
00
09
05
1=
1:
b1000 !
b1000 *
0/
0%
b0 $
b0 )
b1000 #
b1000 (
b1000 &
b0 '
#5160
b1001 !
b1001 *
1/
1%
#5180
1-
b1001 !
b1001 *
1/
0%
b1 $
b1 )
b1 '
#5200
14
12
bz001 +
1.
b1010 !
b1010 *
0/
1%
#5220
09
07
02
03
bz000 +
0.
0-
14
11
b1010 !
b1010 *
0/
0%
b10 $
b10 )
b10 '
#5240
b1011 !
b1011 *
1/
1%
#5260
1-
b1011 !
b1011 *
1/
0%
b11 $
b11 )
b11 '
#5280
19
17
13
04
12
bz011 +
1.
b1100 !
b1100 *
0/
1%
#5300
0"
07
1=
0<
02
03
08
bz000 +
0.
0-
04
01
19
16
b1100 !
b1100 *
0/
0%
b100 $
b100 )
b100 '
#5320
b1101 !
b1101 *
1/
1%
#5340
1-
b1101 !
b1101 *
1/
0%
b101 $
b101 )
b101 '
#5360
14
12
bz001 +
1.
b1110 !
b1110 *
0/
1%
#5380
0"
1=
0<
08
19
07
02
03
bz000 +
0.
0-
14
11
b1110 !
b1110 *
0/
0%
b110 $
b110 )
b110 '
#5400
b1111 !
b1111 *
1/
1%
#5420
1-
b1111 !
b1111 *
1/
0%
b111 $
b111 )
b111 '
#5440
1"
0=
1<
18
09
17
13
04
12
bz111 +
1.
b0 !
b0 *
0/
1%
#5460
07
0<
02
03
08
bz000 +
0.
0-
04
01
09
06
0=
1;
b0 !
b0 *
0/
0%
b1000 $
b1000 )
b1000 '
#5480
b1 !
b1 *
1/
1%
#5500
1-
b1 !
b1 *
1/
0%
b1001 $
b1001 )
b1001 '
#5520
14
12
bz001 +
1.
b10 !
b10 *
0/
1%
#5540
09
07
02
03
bz000 +
0.
0-
14
11
b10 !
b10 *
0/
0%
b1010 $
b1010 )
b1010 '
#5560
b11 !
b11 *
1/
1%
#5580
1-
b11 !
b11 *
1/
0%
b1011 $
b1011 )
b1011 '
#5600
19
17
13
04
12
bz011 +
1.
b100 !
b100 *
0/
1%
#5620
07
0=
0<
02
03
08
bz000 +
0.
0-
04
01
19
16
b100 !
b100 *
0/
0%
b1100 $
b1100 )
b1100 '
#5640
b101 !
b101 *
1/
1%
#5660
1-
b101 !
b101 *
1/
0%
b1101 $
b1101 )
b1101 '
#5680
14
12
bz001 +
1.
b110 !
b110 *
0/
1%
#5700
0=
0<
08
19
07
02
03
bz000 +
0.
0-
14
11
b110 !
b110 *
0/
0%
b1110 $
b1110 )
b1110 '
#5720
b111 !
b111 *
1/
1%
#5740
1-
b111 !
b111 *
1/
0%
b1111 $
b1111 )
b1111 '
#5760
1=
1<
18
09
17
13
04
12
bz111 +
1.
b1000 !
b1000 *
0/
1%
#5780
0"
07
0<
02
03
08
bz000 +
0.
0-
04
01
09
06
1=
0;
1,
b1001 !
b1001 *
1/
0%
b0 $
b0 )
b1001 #
b1001 (
b1001 &
b0 '
#5800
14
12
bz001 +
1.
b1010 !
b1010 *
0/
1%
#5820
1-
b1010 !
b1010 *
0/
0%
b1 $
b1 )
b1 '
#5840
b1011 !
b1011 *
1/
1%
#5860
02
09
07
0.
bz000 +
03
0-
14
11
b1011 !
b1011 *
1/
0%
b10 $
b10 )
b10 '
#5880
19
17
13
04
12
bz011 +
1.
b1100 !
b1100 *
0/
1%
#5900
1-
b1100 !
b1100 *
0/
0%
b11 $
b11 )
b11 '
#5920
b1101 !
b1101 *
1/
1%
#5940
0"
02
07
1=
0<
0.
03
bz000 +
08
0-
04
01
19
16
b1101 !
b1101 *
1/
0%
b100 $
b100 )
b100 '
#5960
14
12
bz001 +
1.
b1110 !
b1110 *
0/
1%
#5980
1-
b1110 !
b1110 *
0/
0%
b101 $
b101 )
b101 '
#6000
b1111 !
b1111 *
1/
1%
#6020
0"
1=
0<
08
02
19
07
0.
bz000 +
03
0-
14
11
b1111 !
b1111 *
1/
0%
b110 $
b110 )
b110 '
#6040
1"
0=
1<
18
09
17
13
04
12
bz111 +
1.
b0 !
b0 *
0/
1%
#6060
1-
b0 !
b0 *
0/
0%
b111 $
b111 )
b111 '
#6080
b1 !
b1 *
1/
1%
#6100
02
07
0<
0.
03
bz000 +
08
0-
04
01
09
06
0=
1;
b1 !
b1 *
1/
0%
b1000 $
b1000 )
b1000 '
#6120
14
12
bz001 +
1.
b10 !
b10 *
0/
1%
#6140
1-
b10 !
b10 *
0/
0%
b1001 $
b1001 )
b1001 '
#6160
b11 !
b11 *
1/
1%
