components/adder/adder.v
// Created by Kavan Heppenstall, 22/08/2024

module adder1bit(A, B, C_in, S, C_out);

input A, B, C_in;
output S, C_out;

assign S = A + B + C_in;

assign C_out = (A & B) | (A & C_in) | (B & C_in);

endmodule

module adder4bit(A, B, C_in, S, C_out);

input [3:0] A, B;
input C_in;

output [3:0] S;
output C_out;

wire [3:0] C_internal;

adder1bit A0(.A(A[0]), .B(B[0]), .C_in(C_in), .S(S[0]), .C_out(C_internal[0]));

adder1bit A1(.A(A[1]), .B(B[1]), .C_in(C_internal[0]), .S(S[1]), .C_out(C_internal[1]));

adder1bit A2(.A(A[2]), .B(B[2]), .C_in(C_internal[1]), .S(S[2]), .C_out(C_internal[2]));

adder1bit A3(.A(A[3]), .B(B[3]), .C_in(C_internal[2]), .S(S[3]), .C_out(C_out));


endmodule

module adder16bit(A, B, C_in, S, C_out);

    input [15:0] A, B;
    input C_in;

    output [15:0] S;
    output C_out;

    wire [3:0] C_internal;

    adder4bit A0(.A(A[3:0]), .B(B[3:0]), .C_in(C_in), .S(S[3:0]), .C_out(C_internal[0]));
    
    adder4bit A1(.A(A[7:4]), .B(B[7:4]), .C_in(C_internal[0]), .S(S[7:4]), .C_out(C_internal[1]));
    
    adder4bit A2(.A(A[11:8]), .B(B[11:8]), .C_in(C_internal[1]), .S(S[11:8]), .C_out(C_internal[2]));
    
    adder4bit A3(.A(A[15:12]), .B(B[15:12]), .C_in(C_internal[2]), .S(S[15:12]), .C_out(C_out));


endmodule

components/adder/adder1bit_tb.v
`timescale 1ns/1ns
`include "adder.v"

module adder1bit_tb;

reg A, B, C_in;
wire S, C_out;
integer i;
reg c1, c2, c3;

adder1bit UUT(A, B, C_in, S, C_out);

initial begin
    
    c1 = 1'b1;
    c2 = 1'b1;
    c3 = 1'b1;

    $dumpfile("adder1bit_tb.vcd");
    $dumpvars(0, adder1bit_tb);

    #20;

    // A = 1'b0; B = 1'b0; C_in = 1'b0; #20;
    // A = 1'b0; B = 1'b0; C_in = 1'b1; #20;
    // A = 1'b0; B = 1'b1; C_in = 1'b0; #20;
    // A = 1'b0; B = 1'b1; C_in = 1'b1; #20;

    for (i = 0; i < 8; i = i + 1) begin
        
        if ((i % 4) == 0) begin
            c1 = ~c1;
        end

        if ((i % 2) == 0) begin
            c2 = ~c2;
        end

        if ((i % 1) == 0) begin
            c3 = ~c3;
        end

        A = c1; B = c2; C_in = c3; #20;

    end


    $display("end");

end

endmodule

components/adder/adder1bit_tb.vcd
$date
	Thu Aug 22 13:58:04 2024
$end
$version
	Icarus Verilog
$end
$timescale
	1ns
$end
$scope module adder1bit_tb $end
$var wire 1 ! S $end
$var wire 1 " C_out $end
$var reg 1 # A $end
$var reg 1 $ B $end
$var reg 1 % C_in $end
$var reg 1 & c1 $end
$var reg 1 ' c2 $end
$var reg 1 ( c3 $end
$var integer 32 ) i [31:0] $end
$scope module UUT $end
$var wire 1 # A $end
$var wire 1 $ B $end
$var wire 1 % C_in $end
$var wire 1 " C_out $end
$var wire 1 ! S $end
$upscope $end
$upscope $end
$enddefinitions $end
$comment Show the parameter values. $end
$dumpall
$end
#0
$dumpvars
bx )
1(
1'
1&
x%
x$
x#
x"
x!
$end
#20
0"
0!
0%
0$
0#
0(
0'
0&
b0 )
#40
1!
1%
1(
b1 )
#60
0%
1!
1$
0(
1'
b10 )
#80
1"
0!
1%
1(
b11 )
#100
0"
0%
0$
1!
1#
0(
0'
1&
b100 )
#120
1"
0!
1%
1(
b101 )
#140
0%
0!
1$
0(
1'
b110 )
#160
1!
1%
1(
b111 )
#180
b1000 )
