components/adder/incrementer.v
// Created by Kavan Heppenstall, 28/08/2024

module pcincrementer(A, clk, Q);

input [15:0] A;
input clk;

output reg [15:0] Q;

always @(posedge clk) begin
    
    Q <= A + 1;

end

endmodule

components/adder/pcincrementer_tb.v
// Created by Kavan Heppenstall, 28/08/2024

`timescale 1ns/1ns
`include "incrementer.v"


module tb;

parameter PERIOD = 10;
parameter RUNTIME = 1000000;

reg clk;

// I/Os

reg [15:0] A;

wire [15:0] Q;


pcincrementer dut(A, clk, Q);


initial begin
    $display("starting simulation");
    clk = 0;
end

always begin
    if ($time > RUNTIME) begin
        $finish;
    end else begin
        #PERIOD clk = ~clk;
    end
end

initial begin

    $dumpfile("pcincrementer_tb.vcd");
    $dumpvars;

end

initial begin // Test Cases
    
    #20;

    A = 16'h0000; #20;
    A = Q; #20;
    A = Q; #20;
    A = Q; #20;
    A = Q; #20;
    A = Q; #20;


    $display("end simulation");

end

endmodule

components/adder/pcincrementer_tb.vcd
$date
	Wed Aug 28 13:23:13 2024
$end
$version
	Icarus Verilog
$end
$timescale
	1ns
$end
$scope module tb $end
$var wire 16 ! Q [15:0] $end
$var parameter 32 " PERIOD $end
$var parameter 32 # RUNTIME $end
$var reg 16 $ A [15:0] $end
$var reg 1 % clk $end
$scope module dut $end
$var wire 16 & A [15:0] $end
$var wire 1 % clk $end
$var reg 16 ' Q [15:0] $end
$upscope $end
$upscope $end
$enddefinitions $end
$comment Show the parameter values. $end
$dumpall
b11110100001001000000 #
b1010 "
$end
#0
$dumpvars
bx '
bx &
0%
bx $
bx !
$end
#10
1%
#20
0%
b0 $
b0 &
#30
b1 !
b1 '
1%
#40
0%
b1 $
b1 &
#50
b10 !
b10 '
1%
#60
0%
b10 $
b10 &
#70
b11 !
b11 '
1%
#80
0%
b11 $
b11 &
#90
b100 !
b100 '
1%
#100
0%
b100 $
b100 &
#110
b101 !
b101 '
1%
#120
0%
b101 $
b101 &
#130
b110 !
b110 '
1%
