components/alu/alu.v
// Created by Kavan Heppenstall, 05/09/2024

`ifdef alu_v
`define alu_v

`include "../adder/adder.v"
`include "../multiplexer/multiplexer.v"

`endif

`ifndef alu_V
`define alu_v

module alu(func, OP0, OP1, flag_en, flag_in, Q, flag_out);

input wire [3:0] func;
input wire [15:0] OP0, OP1;
input wire [3:0] flag_in;
input wire flag_en;

output reg [15:0] Q;
output reg [3:0] flag_out;

reg adder;
wire [15:0] adder_out;
reg [15:0] other;

// multiplexer16bit M0(.A(adder_out), .B(other), .sel(adder), .Q(Q));

// adder16bit ADDER(.A(OP0), .B(OP1), .C_in(flag_in[3]), .S(Q), .C_out(flag_out[3]));

always @(*) begin

    case (func)
        // JMP
        4'b0000: begin
            adder <= 1'b0;
            other <= OP0;
        end
        // ADD
        4'b0001: begin
            if (flag_en) begin
                {flag_out[3], Q} <= {1'b0, OP0} + {1'b0, OP1} + {flag_in[3]};
                {flag_out[2]} <= (Q[15] == 1'b1);           
                {flag_out[1]} <= ((OP0[15] == OP1[15]) && (Q[15] != OP0[15]));
                {flag_out[0]} <= (Q == 16'h0000);
            end else begin
                {Q} <= {1'b0, OP0} + {1'b0, OP1} + {flag_in[3]};
            end
        end
        // SUB
        4'b0010: begin
            if (flag_en) begin
                {flag_out[3], Q} <= {1'b0, OP0} + {1'b0, ~OP1} + {flag_in[3]} + 1'b1;
                {flag_out[2]} <= (Q[15] == 1'b1);           
                {flag_out[1]} <= ((OP0[15] == OP1[15]) && (Q[15] != OP0[15]));
                {flag_out[0]} <= (Q == 16'h0000);
            end else begin
                {Q} <= {1'b0, OP0} + {1'b0, ~OP1} + {flag_in[3]} + 1'b1;
            end
        end
        // LSL
        4'b0011: begin
            if (flag_en) begin
                {Q} <= OP0 << OP1;
                {flag_out[3]} <= OP0[15 - OP1];
                {flag_out[2]} <= (Q[15] == 1'b1);           
                {flag_out[1]} <= (1'b0);
                {flag_out[0]} <= (Q == 16'h0000);
            end else begin
                {Q} <= OP0 << OP1;
            end
        end
        // LSR
        4'b0100: begin
            if (flag_en) begin
                {Q} <= OP0 >> OP1;
                {flag_out[3]} <= OP0[OP1 - 1];
                {flag_out[2]} <= (Q[15] == 1'b1);           
                {flag_out[1]} <= (1'b0);
                {flag_out[0]} <= (Q == 16'h0000);
            end else begin
                {Q} <= OP0 >> OP1;
            end
        end
        // AND
        4'b0101: begin
            if (flag_en) begin
                {Q} <= OP0 & OP1;
                {flag_out[3]} <= (1'b0);
                {flag_out[2]} <= (Q[15] == 1'b1);           
                {flag_out[1]} <= (1'b0);
                {flag_out[0]} <= (Q == 16'h0000);
            end else begin
                {Q} <= OP0 & OP1;
            end
        end
        // OR
        4'b0110: begin
            if (flag_en) begin
                {Q} <= OP0 | OP1;
                {flag_out[3]} <= (1'b0);
                {flag_out[2]} <= (Q[15] == 1'b1);           
                {flag_out[1]} <= (1'b0);
                {flag_out[0]} <= (Q == 16'h0000);
            end else begin
                {Q} <= OP0 | OP1;
            end
        end
        // XOR
        4'b0111: begin
            if (flag_en) begin
                {Q} <= OP0 ^ OP1;
                {flag_out[3]} <= (1'b0);
                {flag_out[2]} <= (Q[15] == 1'b1);           
                {flag_out[1]} <= (1'b0);
                {flag_out[0]} <= (Q == 16'h0000);
            end else begin
                {Q} <= OP0 ^ OP1;
            end
        end
        // LD
        4'b1000: begin
            if (flag_en) begin
                {Q} <= {1'b0, OP0} + {1'b0, OP1} + {flag_in[3]};
                {flag_out[3]} <= (1'b0);
                {flag_out[2]} <= (1'b0);
                {flag_out[1]} <= (1'b0);
                {flag_out[0]} <= (1'b0);
            end else begin
                {Q} <= {1'b0, OP0} + {1'b0, OP1} + {flag_in[3]};
            end
        end
        // ST
        4'b1001: begin
            if (flag_en) begin
                {Q} <= {1'b0, OP0} + {1'b0, OP1};
                {flag_out[3]} <= (1'b0);
                {flag_out[2]} <= (1'b0);
                {flag_out[1]} <= (1'b0);
                {flag_out[0]} <= (1'b0);
            end else begin
                {Q} <= {1'b0, OP0} + {1'b0, OP1};
            end
        end
        // MOV
        4'b1010: begin
            if (flag_en) begin
                {Q} <= {1'b0, OP0} + {1'b0, OP1};
                {flag_out[3]} <= (1'b0);
                {flag_out[2]} <= (1'b0);
                {flag_out[1]} <= (1'b0);
                {flag_out[0]} <= (1'b0);
            end else begin
                {Q} <= {1'b0, OP0} + {1'b0, OP1};
            end
        end
        // BEQ
        4'b1011: begin
            if (flag_in[0] == 1'b1) begin
                {Q} <= {OP0};
            end
        end
        // BNE
        4'b1100: begin
            if (flag_in[0] == 1'b0) begin
                {Q} <= {OP0};
            end
        end
        // BLT
        4'b1101: begin
            if ((flag_in[2] == 1'b1) && (flag_in[0] == 1'b0)) begin
                {Q} <= {OP0};
            end
        end
        // BGT
        4'b1110: begin
            if ((flag_in[2] == 1'b0) && (flag_in[0] == 1'b0)) begin
                {Q} <= {OP0};
            end
        end
        // CMP
        4'b1111: begin
            {flag_out[3], Q} <= {1'b0, OP0} + {1'b0, ~OP1} + {flag_in[3]} + 1'b1;
            {flag_out[2]} <= (Q[15] == 1'b1);           
            {flag_out[1]} <= ((OP0[15] == OP1[15]) && (Q[15] != OP0[15]));
            {flag_out[0]} <= (Q == 16'h0000);
        end
        default: begin
            {flag_out[3], Q} <= 16'hXXXX;
            {flag_out[2]} <= 1'bX;           
            {flag_out[1]} <= 1'bX;
            {flag_out[0]} <= 1'bX;
        end
    endcase

end


endmodule

`endif

components/alu/alu_tb.v
// Created by Kavan Heppenstall, 05/09/2024

`timescale 1ns/1ns
`include "alu.v"


module tb;

parameter PERIOD = 10;
parameter RUNTIME = 1000000;

reg clk;

// I/Os

reg [3:0] FUNC;
reg [15:0] OP0, OP1;
reg flag_en;
reg [3:0] flag_in;

wire [15:0] Q;
wire [3:0] flag_out;


alu dut(.func(FUNC), .OP0(OP0), .OP1(OP1), .flag_en(flag_en), .flag_in(flag_in), .Q(Q), .flag_out(flag_out));


initial begin
    $display("starting simulation");
    clk = 0;
end

always begin
    if ($time > RUNTIME) begin
        $finish;
    end else begin
        #PERIOD clk = ~clk;
    end
end

initial begin

    $dumpfile("alu_tb.vcd");
    $dumpvars;

end

initial begin // Test Cases
    
    #20;

    // JMP 0
    FUNC = 4'b0000; OP0 = 16'h0000; OP1 = 16'h0000; flag_in = 4'b0000; flag_en = 1'b0; #20;
    // ADD 1
    FUNC = 4'b0001; OP0 = 16'h0001; OP1 = 16'h0001; flag_in = 4'b0000; flag_en = 1'b0; #20;
    FUNC = 4'b0001; OP0 = 16'h8001; OP1 = 16'h0001; flag_in = 4'b0000; flag_en = 1'b1; #20;
    // SUB 2
    FUNC = 4'b0010; OP0 = 16'h000A; OP1 = 16'h0005; flag_in = 4'b0000; flag_en = 1'b1; #20;
    FUNC = 4'b0010; OP0 = 16'h0005; OP1 = 16'h000A; flag_in = 4'b0000; flag_en = 1'b1; #20;
    // LSL 3
    FUNC = 4'b0011; OP0 = 16'h0001; OP1 = 16'h0001; flag_in = 4'b0000; flag_en = 1'b1; #20;
    FUNC = 4'b0011; OP0 = 16'h0001; OP1 = 16'h0004; flag_in = 4'b0000; flag_en = 1'b1; #20;
    // LSR 4
    FUNC = 4'b0100; OP0 = 16'h8000; OP1 = 16'h0001; flag_in = 4'b0000; flag_en = 1'b1; #20;
    FUNC = 4'b0100; OP0 = 16'h0001; OP1 = 16'h0001; flag_in = 4'b0000; flag_en = 1'b1; #20;
    // AND 5
    FUNC = 4'b0101; OP0 = 16'h0001; OP1 = 16'h0001; flag_in = 4'b0000; flag_en = 1'b1; #20;
    FUNC = 4'b0101; OP0 = 16'h1100; OP1 = 16'h1001; flag_in = 4'b0000; flag_en = 1'b1; #20;
    // OR 6
    FUNC = 4'b0110; OP0 = 16'h0101; OP1 = 16'h0000; flag_in = 4'b0000; flag_en = 1'b1; #20;
    FUNC = 4'b0110; OP0 = 16'h0001; OP1 = 16'h1001; flag_in = 4'b0000; flag_en = 1'b1; #20;
    // XOR 7
    FUNC = 4'b0111; OP0 = 16'h0001; OP1 = 16'h1001; flag_in = 4'b0000; flag_en = 1'b1; #20;
    FUNC = 4'b0111; OP0 = 16'h0101; OP1 = 16'h0000; flag_in = 4'b0000; flag_en = 1'b1; #20;
    // LD 8
    FUNC = 4'b1000; OP0 = 16'h0001; OP1 = 16'h1001; flag_in = 4'b0000; flag_en = 1'b1; #20;
    FUNC = 4'b1000; OP0 = 16'h0101; OP1 = 16'h0000; flag_in = 4'b0000; flag_en = 1'b1; #20;
    // ST 9
    FUNC = 4'b1001; OP0 = 16'h0001; OP1 = 16'h1001; flag_in = 4'b0000; flag_en = 1'b1; #20;
    FUNC = 4'b1001; OP0 = 16'h0101; OP1 = 16'h0000; flag_in = 4'b0000; flag_en = 1'b1; #20;
    // MOV A
    FUNC = 4'b1010; OP0 = 16'h0001; OP1 = 16'h1001; flag_in = 4'b0000; flag_en = 1'b1; #20;
    FUNC = 4'b1010; OP0 = 16'h0101; OP1 = 16'h0000; flag_in = 4'b0000; flag_en = 1'b1; #20;
    // BEQ B
    FUNC = 4'b1011; OP0 = 16'h0001; OP1 = 16'h1001; flag_in = 4'b0000; flag_en = 1'b1; #20;
    FUNC = 4'b1011; OP0 = 16'h0101; OP1 = 16'h0000; flag_in = 4'b0000; flag_en = 1'b1; #20;
    // BNE C
    FUNC = 4'b1100; OP0 = 16'h0001; OP1 = 16'h1001; flag_in = 4'b0000; flag_en = 1'b1; #20;
    FUNC = 4'b1100; OP0 = 16'h0101; OP1 = 16'h0000; flag_in = 4'b0000; flag_en = 1'b1; #20;
    // BLT D
    FUNC = 4'b1101; OP0 = 16'h0001; OP1 = 16'h1001; flag_in = 4'b0000; flag_en = 1'b1; #20;
    FUNC = 4'b1101; OP0 = 16'h0101; OP1 = 16'h0000; flag_in = 4'b0000; flag_en = 1'b1; #20;
    // BGT E
    FUNC = 4'b1110; OP0 = 16'h0001; OP1 = 16'h1001; flag_in = 4'b0000; flag_en = 1'b1; #20;
    FUNC = 4'b1110; OP0 = 16'h0101; OP1 = 16'h0000; flag_in = 4'b0000; flag_en = 1'b1; #20;
    // CMP F
    FUNC = 4'b1111; OP0 = 16'h0001; OP1 = 16'h1001; flag_in = 4'b0000; flag_en = 1'b1; #20;
    FUNC = 4'b1111; OP0 = 16'h0101; OP1 = 16'h0000; flag_in = 4'b0000; flag_en = 1'b1; #20;

    $display("end simulation");

end

endmodule

components/multiplexer/multiplexer.v
// Created by Kavan Heppenstall, 23/08/2024

module multiplexer1bit(A, B, sel, Q);

input A, B, sel;

output Q;

assign Q =  (sel) ? A:
            (~sel) ? B:
            1'bX;

endmodule

module multiplexer2bit(A, B, C, D, sel, Q);

input A, B, C, D;
input [1:0] sel;

output Q;

assign Q =  (~sel[1] & ~sel[0]) ? A:
            (~sel[1] & sel[0]) ? B:
            (sel[1] & ~sel[0]) ? C:
            (sel[1] & sel[0]) ? D:
            1'bX;

endmodule

module multiplexer4bit(A, B, sel, Q);

input [3:0] A, B;
input sel;

output [3:0] Q;

assign Q =  (sel) ? A:
            (~sel) ? B:
            4'bXXXX;

endmodule

module multiplexer16bit(A, B, sel, Q);

input [15:0] A, B;
input sel;

output [15:0] Q;

assign Q =  (sel) ? A:
            (~sel) ? B:
            16'hXXXX;

endmodule


module multiplexer8to2(A, B, C, D, E, F, G, H, sel0, sel1, Q0, Q1);

input [15:0] A, B, C, D, E, F, G, H;
input [2:0] sel0, sel1;

output [15:0] Q0, Q1;

assign Q0 =  (sel0 == 3'b111) ? A:
            (sel0 == 3'b110) ? B:
            (sel0 == 3'b101) ? C:
            (sel0 == 3'b100) ? D:
            (sel0 == 3'b011) ? E:
            (sel0 == 3'b010) ? F:
            (sel0 == 3'b001) ? G:
            (sel0 == 3'b000) ? H:
            16'hXXXX;

assign Q1 =  (sel1 == 3'b111) ? A:
            (sel1 == 3'b110) ? B:
            (sel1 == 3'b101) ? C:
            (sel1 == 3'b100) ? D:
            (sel1 == 3'b011) ? E:
            (sel1 == 3'b010) ? F:
            (sel1 == 3'b001) ? G:
            (sel1 == 3'b000) ? H:
            16'hXXXX;            

endmodule

components/adder/adder.v
// Created by Kavan Heppenstall, 22/08/2024

module adder1bit(A, B, C_in, S, C_out);

input A, B, C_in;
output S, C_out;

assign S = A + B + C_in;

assign C_out = (A & B) | (A & C_in) | (B & C_in);

endmodule

module adder4bit(A, B, C_in, S, C_out);

input [3:0] A, B;
input C_in;

output [3:0] S;
output C_out;

wire [3:0] C_internal;

adder1bit A0(.A(A[0]), .B(B[0]), .C_in(C_in), .S(S[0]), .C_out(C_internal[0]));

adder1bit A1(.A(A[1]), .B(B[1]), .C_in(C_internal[0]), .S(S[1]), .C_out(C_internal[1]));

adder1bit A2(.A(A[2]), .B(B[2]), .C_in(C_internal[1]), .S(S[2]), .C_out(C_internal[2]));

adder1bit A3(.A(A[3]), .B(B[3]), .C_in(C_internal[2]), .S(S[3]), .C_out(C_out));


endmodule

module adder16bit(A, B, C_in, S, C_out);

    input [15:0] A, B;
    input C_in;

    output [15:0] S;
    output C_out;

    wire [3:0] C_internal;

    adder4bit A0(.A(A[3:0]), .B(B[3:0]), .C_in(C_in), .S(S[3:0]), .C_out(C_internal[0]));
    
    adder4bit A1(.A(A[7:4]), .B(B[7:4]), .C_in(C_internal[0]), .S(S[7:4]), .C_out(C_internal[1]));
    
    adder4bit A2(.A(A[11:8]), .B(B[11:8]), .C_in(C_internal[1]), .S(S[11:8]), .C_out(C_internal[2]));
    
    adder4bit A3(.A(A[15:12]), .B(B[15:12]), .C_in(C_internal[2]), .S(S[15:12]), .C_out(C_out));


endmodule

components/alu/alu_tb.vcd
$date
	Fri Sep 06 10:21:16 2024
$end
$version
	Icarus Verilog
$end
$timescale
	1ns
$end
$scope module adder16bit $end
$var wire 16 ! A [15:0] $end
$var wire 16 " B [15:0] $end
$var wire 1 # C_in $end
$var wire 16 $ S [15:0] $end
$var wire 1 % C_out $end
$var wire 4 & C_internal [3:0] $end
$scope module A0 $end
$var wire 4 ' A [3:0] $end
$var wire 4 ( B [3:0] $end
$var wire 1 # C_in $end
$var wire 4 ) S [3:0] $end
$var wire 1 * C_out $end
$var wire 4 + C_internal [3:0] $end
$scope module A0 $end
$var wire 1 , A $end
$var wire 1 - B $end
$var wire 1 # C_in $end
$var wire 1 . C_out $end
$var wire 1 / S $end
$upscope $end
$scope module A1 $end
$var wire 1 0 A $end
$var wire 1 1 B $end
$var wire 1 2 C_in $end
$var wire 1 3 C_out $end
$var wire 1 4 S $end
$upscope $end
$scope module A2 $end
$var wire 1 5 A $end
$var wire 1 6 B $end
$var wire 1 7 C_in $end
$var wire 1 8 C_out $end
$var wire 1 9 S $end
$upscope $end
$scope module A3 $end
$var wire 1 : A $end
$var wire 1 ; B $end
$var wire 1 < C_in $end
$var wire 1 * C_out $end
$var wire 1 = S $end
$upscope $end
$upscope $end
$scope module A1 $end
$var wire 4 > A [3:0] $end
$var wire 4 ? B [3:0] $end
$var wire 1 @ C_in $end
$var wire 4 A S [3:0] $end
$var wire 1 B C_out $end
$var wire 4 C C_internal [3:0] $end
$scope module A0 $end
$var wire 1 D A $end
$var wire 1 E B $end
$var wire 1 @ C_in $end
$var wire 1 F C_out $end
$var wire 1 G S $end
$upscope $end
$scope module A1 $end
$var wire 1 H A $end
$var wire 1 I B $end
$var wire 1 J C_in $end
$var wire 1 K C_out $end
$var wire 1 L S $end
$upscope $end
$scope module A2 $end
$var wire 1 M A $end
$var wire 1 N B $end
$var wire 1 O C_in $end
$var wire 1 P C_out $end
$var wire 1 Q S $end
$upscope $end
$scope module A3 $end
$var wire 1 R A $end
$var wire 1 S B $end
$var wire 1 T C_in $end
$var wire 1 B C_out $end
$var wire 1 U S $end
$upscope $end
$upscope $end
$scope module A2 $end
$var wire 4 V A [3:0] $end
$var wire 4 W B [3:0] $end
$var wire 1 X C_in $end
$var wire 4 Y S [3:0] $end
$var wire 1 Z C_out $end
$var wire 4 [ C_internal [3:0] $end
$scope module A0 $end
$var wire 1 \ A $end
$var wire 1 ] B $end
$var wire 1 X C_in $end
$var wire 1 ^ C_out $end
$var wire 1 _ S $end
$upscope $end
$scope module A1 $end
$var wire 1 ` A $end
$var wire 1 a B $end
$var wire 1 b C_in $end
$var wire 1 c C_out $end
$var wire 1 d S $end
$upscope $end
$scope module A2 $end
$var wire 1 e A $end
$var wire 1 f B $end
$var wire 1 g C_in $end
$var wire 1 h C_out $end
$var wire 1 i S $end
$upscope $end
$scope module A3 $end
$var wire 1 j A $end
$var wire 1 k B $end
$var wire 1 l C_in $end
$var wire 1 Z C_out $end
$var wire 1 m S $end
$upscope $end
$upscope $end
$scope module A3 $end
$var wire 4 n A [3:0] $end
$var wire 4 o B [3:0] $end
$var wire 1 p C_in $end
$var wire 4 q S [3:0] $end
$var wire 1 % C_out $end
$var wire 4 r C_internal [3:0] $end
$scope module A0 $end
$var wire 1 s A $end
$var wire 1 t B $end
$var wire 1 p C_in $end
$var wire 1 u C_out $end
$var wire 1 v S $end
$upscope $end
$scope module A1 $end
$var wire 1 w A $end
$var wire 1 x B $end
$var wire 1 y C_in $end
$var wire 1 z C_out $end
$var wire 1 { S $end
$upscope $end
$scope module A2 $end
$var wire 1 | A $end
$var wire 1 } B $end
$var wire 1 ~ C_in $end
$var wire 1 !" C_out $end
$var wire 1 "" S $end
$upscope $end
$scope module A3 $end
$var wire 1 #" A $end
$var wire 1 $" B $end
$var wire 1 %" C_in $end
$var wire 1 % C_out $end
$var wire 1 &" S $end
$upscope $end
$upscope $end
$upscope $end
$scope module multiplexer16bit $end
$var wire 16 '" A [15:0] $end
$var wire 16 (" B [15:0] $end
$var wire 1 )" sel $end
$var wire 16 *" Q [15:0] $end
$upscope $end
$scope module multiplexer1bit $end
$var wire 1 +" A $end
$var wire 1 ," B $end
$var wire 1 -" sel $end
$var wire 1 ." Q $end
$upscope $end
$scope module multiplexer2bit $end
$var wire 1 /" A $end
$var wire 1 0" B $end
$var wire 1 1" C $end
$var wire 1 2" D $end
$var wire 2 3" sel [1:0] $end
$var wire 1 4" Q $end
$upscope $end
$scope module multiplexer8to2 $end
$var wire 16 5" A [15:0] $end
$var wire 16 6" B [15:0] $end
$var wire 16 7" C [15:0] $end
$var wire 16 8" D [15:0] $end
$var wire 16 9" E [15:0] $end
$var wire 16 :" F [15:0] $end
$var wire 16 ;" G [15:0] $end
$var wire 16 <" H [15:0] $end
$var wire 3 =" sel0 [2:0] $end
$var wire 3 >" sel1 [2:0] $end
$var wire 16 ?" Q1 [15:0] $end
$var wire 16 @" Q0 [15:0] $end
$upscope $end
$scope module tb $end
$var wire 4 A" flag_out [3:0] $end
$var wire 16 B" Q [15:0] $end
$var parameter 32 C" PERIOD $end
$var parameter 32 D" RUNTIME $end
$var reg 4 E" FUNC [3:0] $end
$var reg 16 F" OP0 [15:0] $end
$var reg 16 G" OP1 [15:0] $end
$var reg 1 H" clk $end
$var reg 1 I" flag_en $end
$var reg 4 J" flag_in [3:0] $end
$scope module dut $end
$var wire 16 K" OP0 [15:0] $end
$var wire 16 L" OP1 [15:0] $end
$var wire 1 I" flag_en $end
$var wire 4 M" flag_in [3:0] $end
$var wire 4 N" func [3:0] $end
$var reg 16 O" Q [15:0] $end
$var reg 1 P" adder $end
$var reg 4 Q" flag_out [3:0] $end
$var reg 16 R" other [15:0] $end
$upscope $end
$upscope $end
$enddefinitions $end
$comment Show the parameter values. $end
$dumpall
b11110100001001000000 D"
b1010 C"
$end
#0
$dumpvars
bx R"
bx Q"
xP"
bx O"
bx N"
bx M"
bx L"
bx K"
bx J"
xI"
0H"
bx G"
bx F"
bx E"
bx B"
bx A"
bx @"
bx ?"
bz >"
bz ="
bz <"
bz ;"
bz :"
bz 9"
bz 8"
bz 7"
bz 6"
bz 5"
x4"
bz 3"
z2"
z1"
z0"
z/"
x."
z-"
z,"
z+"
bx *"
z)"
bz ("
bz '"
x&"
x%"
z$"
z#"
x""
x!"
x~
z}
z|
x{
xz
xy
zx
zw
xv
xu
zt
zs
bzxxx r
bx q
xp
bz o
bz n
xm
xl
zk
zj
xi
xh
xg
zf
ze
xd
xc
xb
za
z`
x_
x^
z]
z\
bzxxx [
xZ
bx Y
xX
bz W
bz V
xU
xT
zS
zR
xQ
xP
xO
zN
zM
xL
xK
xJ
zI
zH
xG
xF
zE
zD
bzxxx C
xB
bx A
x@
bz ?
bz >
x=
x<
z;
z:
x9
x8
x7
z6
z5
x4
x3
x2
z1
z0
x/
x.
z-
z,
bzxxx +
x*
bx )
bz (
bz '
bzxxx &
x%
bx $
z#
bz "
bz !
$end
#10
1H"
#20
b0 R"
0P"
0H"
0I"
b0 J"
b0 M"
b0 G"
b0 L"
b0 F"
b0 K"
b0 E"
b0 N"
#30
1H"
#40
b10 B"
b10 O"
0H"
b1 G"
b1 L"
b1 F"
b1 K"
b1 E"
b1 N"
#50
1H"
#60
b100 A"
b100 Q"
b1000000000000010 B"
b1000000000000010 O"
0H"
1I"
b1000000000000001 F"
b1000000000000001 K"
#70
1H"
#80
b1000 A"
b1000 Q"
b101 B"
b101 O"
0H"
b101 G"
b101 L"
b1010 F"
b1010 K"
b10 E"
b10 N"
#90
1H"
#100
b110 A"
b110 Q"
b1111111111111011 B"
b1111111111111011 O"
0H"
b1010 G"
b1010 L"
b101 F"
b101 K"
#110
1H"
#120
b0 A"
b0 Q"
b10 B"
b10 O"
0H"
b1 G"
b1 L"
b1 F"
b1 K"
b11 E"
b11 N"
#130
1H"
#140
b10000 B"
b10000 O"
0H"
b100 G"
b100 L"
#150
1H"
#160
b100000000000000 B"
b100000000000000 O"
0H"
b1 G"
b1 L"
b1000000000000000 F"
b1000000000000000 K"
b100 E"
b100 N"
#170
1H"
#180
b1001 A"
b1001 Q"
b0 B"
b0 O"
0H"
b1 F"
b1 K"
#190
1H"
#200
b0 A"
b0 Q"
b1 B"
b1 O"
0H"
b101 E"
b101 N"
#210
1H"
#220
b1000000000000 B"
b1000000000000 O"
0H"
b1000000000001 G"
b1000000000001 L"
b1000100000000 F"
b1000100000000 K"
#230
1H"
#240
b100000001 B"
b100000001 O"
0H"
b0 G"
b0 L"
b100000001 F"
b100000001 K"
b110 E"
b110 N"
#250
1H"
#260
b1000000000001 B"
b1000000000001 O"
0H"
b1000000000001 G"
b1000000000001 L"
b1 F"
b1 K"
#270
1H"
#280
b1000000000000 B"
b1000000000000 O"
0H"
b111 E"
b111 N"
#290
1H"
#300
b100000001 B"
b100000001 O"
0H"
b0 G"
b0 L"
b100000001 F"
b100000001 K"
#310
1H"
#320
b1000000000010 B"
b1000000000010 O"
0H"
b1000000000001 G"
b1000000000001 L"
b1 F"
b1 K"
b1000 E"
b1000 N"
#330
1H"
#340
b100000001 B"
b100000001 O"
0H"
b0 G"
b0 L"
b100000001 F"
b100000001 K"
#350
1H"
#360
b1000000000010 B"
b1000000000010 O"
0H"
b1000000000001 G"
b1000000000001 L"
b1 F"
b1 K"
b1001 E"
b1001 N"
#370
1H"
#380
b100000001 B"
b100000001 O"
0H"
b0 G"
b0 L"
b100000001 F"
b100000001 K"
#390
1H"
#400
b1000000000010 B"
b1000000000010 O"
0H"
b1000000000001 G"
b1000000000001 L"
b1 F"
b1 K"
b1010 E"
b1010 N"
#410
1H"
#420
b100000001 B"
b100000001 O"
0H"
b0 G"
b0 L"
b100000001 F"
b100000001 K"
#430
1H"
#440
0H"
b1000000000001 G"
b1000000000001 L"
b1 F"
b1 K"
b1011 E"
b1011 N"
#450
1H"
#460
0H"
b0 G"
b0 L"
b100000001 F"
b100000001 K"
#470
1H"
#480
b1 B"
b1 O"
0H"
b1000000000001 G"
b1000000000001 L"
b1 F"
b1 K"
b1100 E"
b1100 N"
#490
1H"
#500
b100000001 B"
b100000001 O"
0H"
b0 G"
b0 L"
b100000001 F"
b100000001 K"
#510
1H"
#520
0H"
b1000000000001 G"
b1000000000001 L"
b1 F"
b1 K"
b1101 E"
b1101 N"
#530
1H"
#540
0H"
b0 G"
b0 L"
b100000001 F"
b100000001 K"
#550
1H"
#560
b1 B"
b1 O"
0H"
b1000000000001 G"
b1000000000001 L"
b1 F"
b1 K"
b1110 E"
b1110 N"
#570
1H"
#580
b100000001 B"
b100000001 O"
0H"
b0 G"
b0 L"
b100000001 F"
b100000001 K"
#590
1H"
#600
b110 A"
b110 Q"
b1111000000000000 B"
b1111000000000000 O"
0H"
b1000000000001 G"
b1000000000001 L"
b1 F"
b1 K"
b1111 E"
b1111 N"
#610
1H"
#620
b1000 A"
b1000 Q"
b100000001 B"
b100000001 O"
0H"
b0 G"
b0 L"
b100000001 F"
b100000001 K"
