memory/memory.v
// Created by Kavan Heppenstall, 30/08/2024

module RAM(A, addr, en, rw, Q);

input [15:0] A;
input [3:0] addr;
input en, rw;

output reg [15:0] Q;

reg clk_en;

wire clk;

initial begin
    clk_en = 1;
end

mem_clk C0(.en(clk_en), .clk_out(clk));

reg [15:0] memory [15:0];

always @(posedge clk) begin

    if(en) begin
        if(rw) begin // READ
            
            Q <= memory[addr];

        end else if (!rw) begin // WRITE
            
            memory[addr] <= A;

        end
    end

end


endmodule


// Memory has its own clock

module mem_clk(en, clk_out);

input en;

output reg clk_out;

initial begin
    clk_out = 0;
end

always begin
    if (en) begin
        #10 clk_out = ~clk_out;
    end else begin
        #10 clk_out = clk_out;
    end        
end

endmodule

memory/RAM_tb.v
// Created by Kavan Heppenstall, 30/08/2024

`timescale 1ns/1ns
`include "memory.v"


module tb;

parameter PERIOD = 10;
parameter RUNTIME = 1000000;

reg clk;

// I/Os

reg [15:0] A;
reg [3:0] addr;
reg en, rw;

wire [15:0] Q;

RAM dut(.A(A), .addr(addr), .en(en), .rw(rw), .Q(Q));


initial begin
    $display("starting simulation");
    clk = 0;
end

always begin
    if ($time > RUNTIME) begin
        $finish;
    end else begin
        #PERIOD clk = ~clk;
    end
end

initial begin

    $dumpfile("RAM_tb.vcd");
    $dumpvars;

end

initial begin // Test Cases
    
    #20;

    A = 16'h0000; addr = 4'h0; en = 1'b0; rw = 1'b0; #20;
    A = 16'hABCD; addr = 4'h0; en = 1'b1; rw = 1'b0; #20;
    A = 16'hFFEE; addr = 4'h1; en = 1'b1; rw = 1'b0; #20;
    A = 16'hEEEE; addr = 4'h4; en = 1'b1; rw = 1'b0; #20;
    A = 16'h0000; addr = 4'h1; en = 1'b1; rw = 1'b1; #20;
    A = 16'h0000; addr = 4'h0; en = 1'b1; rw = 1'b1; #20;
    A = 16'h0000; addr = 4'h4; en = 1'b1; rw = 1'b1; #20;
    A = 16'h0000; addr = 4'h0; en = 1'b0; rw = 1'b0; #20;


    $display("end simulation");

end

endmodule

memory/RAM_tb.vcd
$date
	Fri Aug 30 16:01:03 2024
$end
$version
	Icarus Verilog
$end
$timescale
	1ns
$end
$scope module tb $end
$var wire 16 ! Q [15:0] $end
$var parameter 32 " PERIOD $end
$var parameter 32 # RUNTIME $end
$var reg 16 $ A [15:0] $end
$var reg 4 % addr [3:0] $end
$var reg 1 & clk $end
$var reg 1 ' en $end
$var reg 1 ( rw $end
$scope module dut $end
$var wire 16 ) A [15:0] $end
$var wire 4 * addr [3:0] $end
$var wire 1 ' en $end
$var wire 1 ( rw $end
$var wire 1 + clk $end
$var reg 16 , Q [15:0] $end
$var reg 1 - clk_en $end
$scope module C0 $end
$var wire 1 - en $end
$var reg 1 + clk_out $end
$upscope $end
$upscope $end
$upscope $end
$enddefinitions $end
$comment Show the parameter values. $end
$dumpall
b11110100001001000000 #
b1010 "
$end
#0
$dumpvars
1-
bx ,
0+
bx *
bx )
x(
x'
0&
bx %
bx $
bx !
$end
#10
1&
#20
0&
1+
0(
0'
b0 %
b0 *
b0 $
b0 )
#30
1&
0+
#40
0&
1+
1'
b1010101111001101 $
b1010101111001101 )
#50
1&
0+
#60
0&
1+
b1 %
b1 *
b1111111111101110 $
b1111111111101110 )
#70
1&
0+
#80
0&
1+
b100 %
b100 *
b1110111011101110 $
b1110111011101110 )
#90
1&
0+
#100
b1111111111101110 !
b1111111111101110 ,
0&
1+
1(
b1 %
b1 *
b0 $
b0 )
#110
1&
0+
#120
b1010101111001101 !
b1010101111001101 ,
0&
1+
b0 %
b0 *
#130
1&
0+
#140
b1110111011101110 !
b1110111011101110 ,
0&
1+
b100 %
b100 *
#150
1&
0+
#160
0&
1+
0(
0'
b0 %
b0 *
