memory/memory.v
// Created by Kavan Heppenstall, 30/08/2024

module RAM(A, addr, en, rw, Q);

input [15:0] A;
input [15:0] addr;
input en, rw;

reg [15:0] memory [511:0];

output reg [15:0] Q;

reg clk_en;

wire clk;

reg[8*8-1:0] str;
reg res;
integer mem_file;
integer scan_file;
integer count;

initial begin
    clk_en = 1;
    count = 0;

    mem_file = $fopen("memory.txt", "r");
    if (mem_file == 0) begin
        mem_file = $fopen("../memory/memory.txt", "r");
        if (mem_file == 0) begin
            $display("memory file handle was NULL");
            $finish;
        end
    end

    while (! $feof(mem_file)) begin
        
        res = $fgets(str, mem_file);

        if(res) begin
            
            scan_file = $sscanf(str, "%h", memory[count]);

            if (scan_file == 1) begin
                $display("Loaded Memory[%0d]: %h", count, memory[count]);
                count = count + 1;
            end else begin
                $display("Error reading line %0d", count);
            end

        end
    end

    $fclose(mem_file);

end

mem_clk C0(.en(clk_en), .clk_out(clk));

always @(posedge clk) begin

    if(en) begin
        if(rw) begin // READ
            
            Q <= memory[addr];

        end else if (!rw) begin // WRITE
            
            memory[addr] <= A;

        end
    end

end


endmodule


// Memory has its own clock

module mem_clk(en, clk_out);

input en;

output reg clk_out;

initial begin
    clk_out = 0;
end

always begin
    if (en) begin
        #10 clk_out = ~clk_out;
    end else begin
        #10 clk_out = clk_out;
    end        
end

endmodule

memory/RAM_tb.v
// Created by Kavan Heppenstall, 30/08/2024

`timescale 1ns/1ns
`include "memory.v"


module tb;

parameter PERIOD = 10;
parameter RUNTIME = 1000000;

reg clk;

// I/Os

reg [15:0] A;
reg [15:0] addr;
reg en, rw;

wire [15:0] Q;

RAM dut(.A(A), .addr(addr), .en(en), .rw(rw), .Q(Q));


initial begin
    $display("starting simulation");
    clk = 0;
end

always begin
    if ($time > RUNTIME) begin
        $finish;
    end else begin
        #PERIOD clk = ~clk;
    end
end

initial begin

    $dumpfile("RAM_tb.vcd");
    $dumpvars;

end

initial begin // Test Cases
    
    #20;

    A = 16'h0000; addr = 16'h0000; en = 1'b1; rw = 1'b1; #20;
    A = 16'h0000; addr = 16'h0001; en = 1'b1; rw = 1'b1; #20;
    A = 16'h0000; addr = 16'h0002; en = 1'b1; rw = 1'b1; #20;
    A = 16'h0000; addr = 16'h0003; en = 1'b1; rw = 1'b1; #20;
    A = 16'h0000; addr = 16'h0004; en = 1'b1; rw = 1'b1; #20;
    A = 16'h0000; addr = 16'h000F; en = 1'b1; rw = 1'b1; #20;
    A = 16'h0000; addr = 16'h0011; en = 1'b1; rw = 1'b1; #20;
    A = 16'h0F0F; addr = 16'h0011; en = 1'b1; rw = 1'b0; #20;
    A = 16'h0000; addr = 16'h0011; en = 1'b1; rw = 1'b1; #20;


    $display("end simulation");

end

endmodule

memory/RAM_tb.vcd
$date
	Fri Sep 06 11:21:05 2024
$end
$version
	Icarus Verilog
$end
$timescale
	1ns
$end
$scope module tb $end
$var wire 16 ! Q [15:0] $end
$var parameter 32 " PERIOD $end
$var parameter 32 # RUNTIME $end
$var reg 16 $ A [15:0] $end
$var reg 16 % addr [15:0] $end
$var reg 1 & clk $end
$var reg 1 ' en $end
$var reg 1 ( rw $end
$scope module dut $end
$var wire 16 ) A [15:0] $end
$var wire 16 * addr [15:0] $end
$var wire 1 ' en $end
$var wire 1 ( rw $end
$var wire 1 + clk $end
$var reg 16 , Q [15:0] $end
$var reg 1 - clk_en $end
$var reg 1 . res $end
$var reg 64 / str [63:0] $end
$var integer 32 0 count [31:0] $end
$var integer 32 1 mem_file [31:0] $end
$var integer 32 2 scan_file [31:0] $end
$scope module C0 $end
$var wire 1 - en $end
$var reg 1 + clk_out $end
$upscope $end
$upscope $end
$upscope $end
$enddefinitions $end
$comment Show the parameter values. $end
$dumpall
b11110100001001000000 #
b1010 "
$end
#0
$dumpvars
b1 2
b10000000000000000000000000000011 1
b10010 0
b110000001100000011000000110000 /
0.
1-
bx ,
0+
bx *
bx )
x(
x'
0&
bx %
bx $
bx !
$end
#10
1&
#20
b1000000000111101 !
b1000000000111101 ,
0&
1+
1(
1'
b0 %
b0 *
b0 $
b0 )
#30
1&
0+
#40
b1000000111101 !
b1000000111101 ,
0&
1+
b1 %
b1 *
#50
1&
0+
#60
b1001000000111101 !
b1001000000111101 ,
0&
1+
b10 %
b10 *
#70
1&
0+
#80
0&
1+
b11 %
b11 *
#90
1&
0+
#100
0&
1+
b100 %
b100 *
#110
1&
0+
#120
b1110111011101110 !
b1110111011101110 ,
0&
1+
b1111 %
b1111 *
#130
1&
0+
#140
0&
1+
b10001 %
b10001 *
#150
1&
0+
#160
0&
1+
0(
b111100001111 $
b111100001111 )
#170
1&
0+
#180
b111100001111 !
b111100001111 ,
0&
1+
1(
b0 $
b0 )
