components/line_decoder/decoder4to16_tb.v
// Created by Kavan Heppenstall, 23/08/2024

`timescale 1ns/1ns
`include "decoder.v"


module tb;

parameter PERIOD = 10;
parameter RUNTIME = 1000000;

reg clk;

// I/Os

reg [3:0] A;
reg en;

wire [15:0] D;

integer i, j;

decoder4to16 dut(.A(A), .en(en), .D(D));


initial begin
    $display("starting simulation");
    clk = 0;
end

always begin
    if ($time > RUNTIME) begin
        $finish;
    end else begin
        #PERIOD clk = ~clk;
    end
end

initial begin

    $dumpfile("decoder4to16_tb.vcd");
    $dumpvars;

end

initial begin // Test Cases
    
    en = 1'b1; #20;

    A = 4'b0000; #20;

    for (i = 0; i < 2; i = i + 1) begin
        for (j = 0; j < 8; j = j + 1) begin
            A[3] = i; A[2:0] = j; #20;
        end
    end

    $display("end simulation");

end

endmodule

components/line_decoder/decoder.v
//Created by Kavan Heppenstall, 22/08/2024


module decoder1to2(A, D);

input A;
output [1:0] D;

assign D[0] = ~A;
assign D[1] = A;

endmodule

module decoder2to4(A, D);

input [1:0] A;
output [3:0] D;

wire [3:0] W;

decoder1to2 U0(.A(A[0]), .D(W[3:2]));

decoder1to2 U1(.A(A[1]), .D(W[1:0]));

assign D[0] = W[3] & W[1];
assign D[1] = W[2] & W[1];
assign D[2] = W[3] & W[0];
assign D[3] = W[2] & W[0];


endmodule


module decoder3to8(A, en, D);

input [2:0] A;
input en;

output [7:0] D;

wire [5:0] W;

decoder1to2 U0(.A(A[0]), .D(W[5:4]));

decoder1to2 U1(.A(A[1]), .D(W[3:2]));

decoder1to2 U2(.A(A[2]), .D(W[1:0]));


assign D[0] = en ? (W[5] & W[3] & W[1]):
              ~en ? 1'b0:
              1'bX;
assign D[1] = en ? (W[4] & W[3] & W[1]):
              ~en ? 1'b0:
              1'bX;
assign D[2] = en ? (W[5] & W[2] & W[1]):
              ~en ? 1'b0:
              1'bX;
assign D[3] = en ? (W[4] & W[2] & W[1]):
              ~en ? 1'b0:
              1'bX;
assign D[4] = en ? (W[5] & W[3] & W[0]):
              ~en ? 1'b0:
              1'bX;
assign D[5] = en ? (W[4] & W[3] & W[0]):
              ~en ? 1'b0:
              1'bX;
assign D[6] = en ? (W[5] & W[2] & W[0]):
              ~en ? 1'b0:
              1'bX;
assign D[7] = en ? (W[4] & W[2] & W[0]):
              ~en ? 1'b0:
              1'bX;


endmodule

module decoder4to16(A, en, D);

input [3:0] A;
input en;

output [15:0] D;

wire [15:0] W;

decoder3to8 U0(.A(A[2:0]), .en(A[3]), .D(D[15:8]));

decoder3to8 U1(.A(A[2:0]), .en(~A[3]), .D(D[7:0]));


endmodule

components/line_decoder/decoder4to16_tb.vcd
$date
	Sat Aug 24 00:22:53 2024
$end
$version
	Icarus Verilog
$end
$timescale
	1ns
$end
$scope module decoder2to4 $end
$var wire 2 ! A [1:0] $end
$var wire 4 " W [3:0] $end
$var wire 4 # D [3:0] $end
$scope module U0 $end
$var wire 1 $ A $end
$var wire 2 % D [1:0] $end
$upscope $end
$scope module U1 $end
$var wire 1 & A $end
$var wire 2 ' D [1:0] $end
$upscope $end
$upscope $end
$scope module tb $end
$var wire 16 ( D [15:0] $end
$var parameter 32 ) PERIOD $end
$var parameter 32 * RUNTIME $end
$var reg 4 + A [3:0] $end
$var reg 1 , clk $end
$var reg 1 - en $end
$var integer 32 . i [31:0] $end
$var integer 32 / j [31:0] $end
$scope module dut $end
$var wire 4 0 A [3:0] $end
$var wire 1 - en $end
$var wire 16 1 D [15:0] $end
$scope module U0 $end
$var wire 3 2 A [2:0] $end
$var wire 1 3 en $end
$var wire 6 4 W [5:0] $end
$var wire 8 5 D [7:0] $end
$scope module U0 $end
$var wire 1 6 A $end
$var wire 2 7 D [1:0] $end
$upscope $end
$scope module U1 $end
$var wire 1 8 A $end
$var wire 2 9 D [1:0] $end
$upscope $end
$scope module U2 $end
$var wire 1 : A $end
$var wire 2 ; D [1:0] $end
$upscope $end
$upscope $end
$scope module U1 $end
$var wire 3 < A [2:0] $end
$var wire 1 = en $end
$var wire 6 > W [5:0] $end
$var wire 8 ? D [7:0] $end
$scope module U0 $end
$var wire 1 @ A $end
$var wire 2 A D [1:0] $end
$upscope $end
$scope module U1 $end
$var wire 1 B A $end
$var wire 2 C D [1:0] $end
$upscope $end
$scope module U2 $end
$var wire 1 D A $end
$var wire 2 E D [1:0] $end
$upscope $end
$upscope $end
$upscope $end
$upscope $end
$enddefinitions $end
$comment Show the parameter values. $end
$dumpall
b11110100001001000000 *
b1010 )
$end
#0
$dumpvars
bx E
xD
bx C
xB
bx A
x@
bx ?
bx >
x=
bx <
bx ;
x:
bx 9
x8
bx 7
x6
bx 5
bx 4
x3
bx 2
bx 1
bx 0
bx /
bx .
1-
0,
bx +
bx (
bz '
z&
bz %
z$
bx #
bz "
bz !
$end
#10
1,
#20
b10000000 ?
b10000000 (
b10000000 1
b0 5
b1 7
06
b1 9
08
b10101 4
b1 ;
0:
b1 A
0@
b1 C
0B
b10101 >
b1 E
0D
1=
b0 2
03
b0 <
0,
b0 +
b0 0
#30
1,
#40
0,
b0 /
b0 .
#50
1,
#60
b1000000 (
b1000000 1
b1000000 ?
b100101 4
b10 7
16
b100101 >
b10 A
1@
b1 2
b1 <
0,
b1 +
b1 0
b1 /
#70
1,
#80
b100000 (
b100000 1
b100000 ?
b1 7
06
b11001 4
b10 9
18
b1 A
0@
b11001 >
b10 C
1B
b10 2
b10 <
0,
b10 +
b10 0
b10 /
#90
1,
#100
b10000 (
b10000 1
b10000 ?
b101001 4
b10 7
16
b101001 >
b10 A
1@
b11 2
b11 <
0,
b11 +
b11 0
b11 /
#110
1,
#120
b1000 (
b1000 1
b1000 ?
b1 7
06
b1 9
08
b10110 4
b10 ;
1:
b1 A
0@
b1 C
0B
b10110 >
b10 E
1D
b100 2
b100 <
0,
b100 +
b100 0
b100 /
#130
1,
#140
b100 (
b100 1
b100 ?
b100110 4
b10 7
16
b100110 >
b10 A
1@
b101 2
b101 <
0,
b101 +
b101 0
b101 /
#150
1,
#160
b10 (
b10 1
b10 ?
b1 7
06
b11010 4
b10 9
18
b1 A
0@
b11010 >
b10 C
1B
b110 2
b110 <
0,
b110 +
b110 0
b110 /
#170
1,
#180
b1 (
b1 1
b1 ?
b101010 4
b10 7
16
b101010 >
b10 A
1@
b111 2
b111 <
0,
b111 +
b111 0
b111 /
#190
1,
#200
b0 ?
b1 7
06
b1 9
08
b10101 4
b1 ;
0:
b1 A
0@
b1 C
0B
b10101 >
b1 E
0D
b1000000000000000 (
b1000000000000000 1
b10000000 5
0=
b0 2
b0 <
13
0,
b1000 +
b1000 0
b1 .
b0 /
#210
1,
#220
b100000000000000 (
b100000000000000 1
b1000000 5
b100101 4
b10 7
16
b100101 >
b10 A
1@
b1 2
b1 <
0,
b1001 +
b1001 0
b1 /
#230
1,
#240
b10000000000000 (
b10000000000000 1
b100000 5
b1 7
06
b11001 4
b10 9
18
b1 A
0@
b11001 >
b10 C
1B
b10 2
b10 <
0,
b1010 +
b1010 0
b10 /
#250
1,
#260
b1000000000000 (
b1000000000000 1
b10000 5
b101001 4
b10 7
16
b101001 >
b10 A
1@
b11 2
b11 <
0,
b1011 +
b1011 0
b11 /
#270
1,
#280
b100000000000 (
b100000000000 1
b1000 5
b1 7
06
b1 9
08
b10110 4
b10 ;
1:
b1 A
0@
b1 C
0B
b10110 >
b10 E
1D
b100 2
b100 <
0,
b1100 +
b1100 0
b100 /
#290
1,
#300
b10000000000 (
b10000000000 1
b100 5
b100110 4
b10 7
16
b100110 >
b10 A
1@
b101 2
b101 <
0,
b1101 +
b1101 0
b101 /
#310
1,
#320
b1000000000 (
b1000000000 1
b10 5
b1 7
06
b11010 4
b10 9
18
b1 A
0@
b11010 >
b10 C
1B
b110 2
b110 <
0,
b1110 +
b1110 0
b110 /
#330
1,
#340
b100000000 (
b100000000 1
b1 5
b101010 4
b10 7
16
b101010 >
b10 A
1@
b111 2
b111 <
0,
b1111 +
b1111 0
b111 /
#350
1,
#360
0,
b10 .
b1000 /
