components/multiplexer/multiplexer2bit_tb.v
// Created by Kavan Heppenstall, 23/08/2024

`timescale 1ns/1ns
`include "multiplexer.v"


module tb;

parameter PERIOD = 10;
parameter RUNTIME = 1000000;

reg clk;

// I/Os

reg A, B, C, D;
reg [1:0] sel;

wire Q;

multiplexer2bit dut(.A(A), .B(B), .C(C), .D(D), .sel(sel), .Q(Q));


initial begin
    $display("starting simulation");
    clk = 0;
end

always begin
    if ($time > RUNTIME) begin
        $finish;
    end else begin
        #PERIOD clk = ~clk;
    end
end

initial begin

    $dumpfile("multiplexer2bit_tb.vcd");
    $dumpvars;

end

initial begin // Test Cases
    
    #20;

    A = 1'b0; B = 1'b0; C = 1'b0; D = 1'b0; sel = 2'b00; #20;
    A = 1'b1; B = 1'b0; C = 1'b0; D = 1'b0; sel = 2'b00; #20;
    A = 1'b0; B = 1'b1; C = 1'b0; D = 1'b0; sel = 2'b01; #20;
    A = 1'b0; B = 1'b0; C = 1'b1; D = 1'b0; sel = 2'b10; #20;
    A = 1'b0; B = 1'b0; C = 1'b0; D = 1'b1; sel = 2'b11; #20;
    A = 1'b0; B = 1'b0; C = 1'b0; D = 1'b0; sel = 2'b11; #20;
    A = 1'b1; B = 1'b1; C = 1'b0; D = 1'b0; sel = 2'b11; #20;
    A = 1'b1; B = 1'b1; C = 1'b1; D = 1'b1; sel = 2'b10; #20;



    $display("end simulation");

end

endmodule

components/multiplexer/multiplexer.v
// Created by Kavan Heppenstall, 23/08/2024

module multiplexer1bit(A, B, sel, Q);

input A, B, sel;

output Q;

assign Q =  (sel) ? A:
            (~sel) ? B:
            1'bX;

endmodule

module multiplexer2bit(A, B, C, D, sel, Q);

input A, B, C, D;
input [1:0] sel;

output Q;

assign Q =  (~sel[1] & ~sel[0]) ? A:
            (~sel[1] & sel[0]) ? B:
            (sel[1] & ~sel[0]) ? C:
            (sel[1] & sel[0]) ? D:
            1'bX;

endmodule

module multiplexer16bit(A, B, sel, Q);

input [15:0] A, B;
input sel;

output [15:0] Q;

assign Q =  (sel) ? A:
            (~sel) ? B:
            16'hXXXX;

endmodule

components/multiplexer/multiplexer2bit_tb.vcd
$date
	Fri Aug 23 22:52:29 2024
$end
$version
	Icarus Verilog
$end
$timescale
	1ns
$end
$scope module multiplexer1bit $end
$var wire 1 ! A $end
$var wire 1 " B $end
$var wire 1 # sel $end
$var wire 1 $ Q $end
$upscope $end
$scope module tb $end
$var wire 1 % Q $end
$var parameter 32 & PERIOD $end
$var parameter 32 ' RUNTIME $end
$var reg 1 ( A $end
$var reg 1 ) B $end
$var reg 1 * C $end
$var reg 1 + D $end
$var reg 1 , clk $end
$var reg 2 - sel [1:0] $end
$scope module dut $end
$var wire 1 ( A $end
$var wire 1 ) B $end
$var wire 1 * C $end
$var wire 1 + D $end
$var wire 2 . sel [1:0] $end
$var wire 1 % Q $end
$upscope $end
$upscope $end
$enddefinitions $end
$comment Show the parameter values. $end
$dumpall
b11110100001001000000 '
b1010 &
$end
#0
$dumpvars
bx .
bx -
0,
x+
x*
x)
x(
x%
x$
z#
z"
z!
$end
#10
1,
#20
0%
0,
b0 -
b0 .
0+
0*
0)
0(
#30
1,
#40
1%
0,
1(
#50
1,
#60
1%
0,
b1 -
b1 .
1)
0(
#70
1,
#80
1%
0,
b10 -
b10 .
1*
0)
#90
1,
#100
1%
0,
b11 -
b11 .
1+
0*
#110
1,
#120
0%
0,
0+
#130
1,
#140
0,
1)
1(
#150
1,
#160
1%
0,
b10 -
b10 .
1+
1*
