components/multiplexer/multiplexer.v
// Created by Kavan Heppenstall, 23/08/2024

module multiplexer1bit(A, B, sel, Q);

input A, B, sel;

output Q;

assign Q =  (sel) ? A:
            (~sel) ? B:
            1'bX;

endmodule

module multiplexer2bit(A, B, C, D, sel, Q);

input A, B, C, D;
input [1:0] sel;

output Q;

assign Q =  (~sel[1] & ~sel[0]) ? A:
            (~sel[1] & sel[0]) ? B:
            (sel[1] & ~sel[0]) ? C:
            (sel[1] & sel[0]) ? D:
            1'bX;

endmodule

module multiplexer16bit(A, B, sel, Q);

input [15:0] A, B;
input sel;

output [15:0] Q;

assign Q =  (sel) ? A:
            (~sel) ? B:
            16'hXXXX;

endmodule

components/multiplexer/multiplexer1bit_tb.v
// Created by Kavan Heppenstall, 23/08/2024

`timescale 1ns/1ns
`include "multiplexer.v"


module tb;

parameter PERIOD = 10;
parameter RUNTIME = 1000000;

reg clk;

// I/Os

reg A, B, sel;

wire Q;

multiplexer1bit dut(A, B, sel, Q);


initial begin
    $display("starting simulation");
    clk = 0;
end

always begin
    if ($time > RUNTIME) begin
        $finish;
    end else begin
        #PERIOD clk = ~clk;
    end
end

initial begin

    $dumpfile("multiplexer1bit_tb.vcd");
    $dumpvars;

end

initial begin // Test Cases
    
    #20;
    A = 1'b0; B = 1'b0; sel = 1'b0; #20;
    A = 1'b1; B = 1'b0; sel = 1'b0; #20;
    A = 1'b1; B = 1'b0; sel = 1'b1; #20;
    A = 1'b0; B = 1'b1; sel = 1'b0; #20;
    A = 1'b0; B = 1'b0; sel = 1'b0; #20;
    A = 1'b1; B = 1'b0; sel = 1'b0; #20;
    A = 1'b1; B = 1'b0; sel = 1'b1; #20;
    A = 1'b1; B = 1'b0; sel = 1'b0; #20;
    A = 1'b1; B = 1'b0; sel = 1'b1; #20;


    $display("end simulation");

end

endmodule

components/multiplexer/multiplexer1bit_tb.vcd
$date
	Fri Aug 23 22:38:49 2024
$end
$version
	Icarus Verilog
$end
$timescale
	1ns
$end
$scope module tb $end
$var wire 1 ! Q $end
$var parameter 32 " PERIOD $end
$var parameter 32 # RUNTIME $end
$var reg 1 $ A $end
$var reg 1 % B $end
$var reg 1 & clk $end
$var reg 1 ' sel $end
$scope module dut $end
$var wire 1 $ A $end
$var wire 1 % B $end
$var wire 1 ' sel $end
$var wire 1 ! Q $end
$upscope $end
$upscope $end
$enddefinitions $end
$comment Show the parameter values. $end
$dumpall
b11110100001001000000 #
b1010 "
$end
#0
$dumpvars
x'
0&
x%
x$
x!
$end
#10
1&
#20
0!
0&
0'
0%
0$
#30
1&
#40
0&
1$
#50
1&
#60
1!
0&
1'
#70
1&
#80
1!
0&
0'
1%
0$
#90
1&
#100
0!
0&
0%
#110
1&
#120
0&
1$
#130
1&
#140
1!
0&
1'
#150
1&
#160
0!
0&
0'
#170
1&
#180
1!
0&
1'
