components/register/register16bit_tb.v
// Created by Kavan Heppenstall, 22/08/2024

`timescale 1ns/1ns
`include "register.v"

module tb;

parameter PERIOD = 10;
parameter RUNTIME = 100000;

reg clk;

reg [15:0] D;
reg en;
reg reset;

wire [15:0] Q;

register16bit dut(.D(D), .clk(clk), .en(en), .reset(reset), .Q(Q));

initial begin
    $display("starting simulation");
    clk = 0;
end

always begin
    if ($time > RUNTIME) begin
        $finish;
    end else begin
        #PERIOD clk = ~clk;
    end
end

initial begin

    $dumpfile("register16bit_tb.vcd");
    $dumpvars;

end

initial begin // Test Cases
    
    #20;

    D = 16'h0000; en = 1'b0; reset = 1'b0; #20;
    D = 16'h0003; en = 1'b1; reset = 1'b0; #20;
    D = 16'h0002; en = 1'b0; reset = 1'b0; #20;
    D = 16'h000D; en = 1'b0; reset = 1'b0; #20;
    D = 16'hXXXX;
    reset = 1'b1; #20;
    reset = 1'b0; #20;

    #20;    


    $display("end simulation");
end



endmodule

components/register/register.v
// Created by Kavan Heppenstall, 22/08/2024

module dflipflop(D, clk, en, reset, Q);

input D, clk, en, reset;

output reg Q;

always @(posedge clk) begin
    
    if (reset) begin

        Q <= 1'b0;

    end

    if (en) begin

        Q <= D;

    end

end


endmodule

module register16bit(D, clk, en, reset, Q);

input [15:0] D;
input en;
input clk, reset;

output [15:0] Q;

genvar i;
generate
    for (i = 0; i < 16; i = i + 1) begin : dff
        dflipflop D (
            .D(D[i]),
            .clk(clk),
            .en(en),
            .reset(reset),
            .Q(Q[i])
        );
    end
endgenerate


endmodule

module register8bit(D, clk, en, Q, reset);

input [7:0] D;
input en;
input clk, reset;

output [7:0] Q;

genvar i;
generate
    for (i = 0; i < 8; i = i + 1) begin : dff
        dflipflop D (
            .D(D[i]),
            .clk(clk),
            .en(en),
            .reset(reset),
            .Q(Q[i])
        );
    end
endgenerate


endmodule

module register4bit(D, clk, en, Q, reset);

input [3:0] D;
input en;
input clk, reset;

output [3:0] Q;

genvar i;
generate
    for (i = 0; i < 4; i = i + 1) begin : dff
        dflipflop D (
            .D(D[i]),
            .clk(clk),
            .en(en),
            .reset(reset),
            .Q(Q[i])
        );
    end
endgenerate


endmodule

module register3bit(D, clk, en, Q, reset);

input [2:0] D;
input en;
input clk, reset;

output [2:0] Q;

genvar i;
generate
    for (i = 0; i < 3; i = i + 1) begin : dff
        dflipflop D (
            .D(D[i]),
            .clk(clk),
            .en(en),
            .reset(reset),
            .Q(Q[i])
        );
    end
endgenerate


endmodule

components/register/register16bit_tb.vcd
$date
	Tue Sep 10 10:40:48 2024
$end
$version
	Icarus Verilog
$end
$timescale
	1ns
$end
$scope module register3bit $end
$var wire 3 ! D [2:0] $end
$var wire 1 " clk $end
$var wire 1 # en $end
$var wire 1 $ reset $end
$var wire 3 % Q [2:0] $end
$scope begin dff[0] $end
$var parameter 2 & i $end
$scope module D $end
$var wire 1 ' D $end
$var wire 1 " clk $end
$var wire 1 # en $end
$var wire 1 $ reset $end
$var reg 1 ( Q $end
$upscope $end
$upscope $end
$scope begin dff[1] $end
$var parameter 2 ) i $end
$scope module D $end
$var wire 1 * D $end
$var wire 1 " clk $end
$var wire 1 # en $end
$var wire 1 $ reset $end
$var reg 1 + Q $end
$upscope $end
$upscope $end
$scope begin dff[2] $end
$var parameter 3 , i $end
$scope module D $end
$var wire 1 - D $end
$var wire 1 " clk $end
$var wire 1 # en $end
$var wire 1 $ reset $end
$var reg 1 . Q $end
$upscope $end
$upscope $end
$upscope $end
$scope module register4bit $end
$var wire 4 / D [3:0] $end
$var wire 1 0 clk $end
$var wire 1 1 en $end
$var wire 1 2 reset $end
$var wire 4 3 Q [3:0] $end
$scope begin dff[0] $end
$var parameter 2 4 i $end
$scope module D $end
$var wire 1 5 D $end
$var wire 1 0 clk $end
$var wire 1 1 en $end
$var wire 1 2 reset $end
$var reg 1 6 Q $end
$upscope $end
$upscope $end
$scope begin dff[1] $end
$var parameter 2 7 i $end
$scope module D $end
$var wire 1 8 D $end
$var wire 1 0 clk $end
$var wire 1 1 en $end
$var wire 1 2 reset $end
$var reg 1 9 Q $end
$upscope $end
$upscope $end
$scope begin dff[2] $end
$var parameter 3 : i $end
$scope module D $end
$var wire 1 ; D $end
$var wire 1 0 clk $end
$var wire 1 1 en $end
$var wire 1 2 reset $end
$var reg 1 < Q $end
$upscope $end
$upscope $end
$scope begin dff[3] $end
$var parameter 3 = i $end
$scope module D $end
$var wire 1 > D $end
$var wire 1 0 clk $end
$var wire 1 1 en $end
$var wire 1 2 reset $end
$var reg 1 ? Q $end
$upscope $end
$upscope $end
$upscope $end
$scope module register8bit $end
$var wire 8 @ D [7:0] $end
$var wire 1 A clk $end
$var wire 1 B en $end
$var wire 1 C reset $end
$var wire 8 D Q [7:0] $end
$scope begin dff[0] $end
$var parameter 2 E i $end
$scope module D $end
$var wire 1 F D $end
$var wire 1 A clk $end
$var wire 1 B en $end
$var wire 1 C reset $end
$var reg 1 G Q $end
$upscope $end
$upscope $end
$scope begin dff[1] $end
$var parameter 2 H i $end
$scope module D $end
$var wire 1 I D $end
$var wire 1 A clk $end
$var wire 1 B en $end
$var wire 1 C reset $end
$var reg 1 J Q $end
$upscope $end
$upscope $end
$scope begin dff[2] $end
$var parameter 3 K i $end
$scope module D $end
$var wire 1 L D $end
$var wire 1 A clk $end
$var wire 1 B en $end
$var wire 1 C reset $end
$var reg 1 M Q $end
$upscope $end
$upscope $end
$scope begin dff[3] $end
$var parameter 3 N i $end
$scope module D $end
$var wire 1 O D $end
$var wire 1 A clk $end
$var wire 1 B en $end
$var wire 1 C reset $end
$var reg 1 P Q $end
$upscope $end
$upscope $end
$scope begin dff[4] $end
$var parameter 4 Q i $end
$scope module D $end
$var wire 1 R D $end
$var wire 1 A clk $end
$var wire 1 B en $end
$var wire 1 C reset $end
$var reg 1 S Q $end
$upscope $end
$upscope $end
$scope begin dff[5] $end
$var parameter 4 T i $end
$scope module D $end
$var wire 1 U D $end
$var wire 1 A clk $end
$var wire 1 B en $end
$var wire 1 C reset $end
$var reg 1 V Q $end
$upscope $end
$upscope $end
$scope begin dff[6] $end
$var parameter 4 W i $end
$scope module D $end
$var wire 1 X D $end
$var wire 1 A clk $end
$var wire 1 B en $end
$var wire 1 C reset $end
$var reg 1 Y Q $end
$upscope $end
$upscope $end
$scope begin dff[7] $end
$var parameter 4 Z i $end
$scope module D $end
$var wire 1 [ D $end
$var wire 1 A clk $end
$var wire 1 B en $end
$var wire 1 C reset $end
$var reg 1 \ Q $end
$upscope $end
$upscope $end
$upscope $end
$scope module tb $end
$var wire 16 ] Q [15:0] $end
$var parameter 32 ^ PERIOD $end
$var parameter 32 _ RUNTIME $end
$var reg 16 ` D [15:0] $end
$var reg 1 a clk $end
$var reg 1 b en $end
$var reg 1 c reset $end
$scope module dut $end
$var wire 16 d D [15:0] $end
$var wire 1 a clk $end
$var wire 1 b en $end
$var wire 1 c reset $end
$var wire 16 e Q [15:0] $end
$scope begin dff[0] $end
$var parameter 2 f i $end
$scope module D $end
$var wire 1 g D $end
$var wire 1 a clk $end
$var wire 1 b en $end
$var wire 1 c reset $end
$var reg 1 h Q $end
$upscope $end
$upscope $end
$scope begin dff[1] $end
$var parameter 2 i i $end
$scope module D $end
$var wire 1 j D $end
$var wire 1 a clk $end
$var wire 1 b en $end
$var wire 1 c reset $end
$var reg 1 k Q $end
$upscope $end
$upscope $end
$scope begin dff[2] $end
$var parameter 3 l i $end
$scope module D $end
$var wire 1 m D $end
$var wire 1 a clk $end
$var wire 1 b en $end
$var wire 1 c reset $end
$var reg 1 n Q $end
$upscope $end
$upscope $end
$scope begin dff[3] $end
$var parameter 3 o i $end
$scope module D $end
$var wire 1 p D $end
$var wire 1 a clk $end
$var wire 1 b en $end
$var wire 1 c reset $end
$var reg 1 q Q $end
$upscope $end
$upscope $end
$scope begin dff[4] $end
$var parameter 4 r i $end
$scope module D $end
$var wire 1 s D $end
$var wire 1 a clk $end
$var wire 1 b en $end
$var wire 1 c reset $end
$var reg 1 t Q $end
$upscope $end
$upscope $end
$scope begin dff[5] $end
$var parameter 4 u i $end
$scope module D $end
$var wire 1 v D $end
$var wire 1 a clk $end
$var wire 1 b en $end
$var wire 1 c reset $end
$var reg 1 w Q $end
$upscope $end
$upscope $end
$scope begin dff[6] $end
$var parameter 4 x i $end
$scope module D $end
$var wire 1 y D $end
$var wire 1 a clk $end
$var wire 1 b en $end
$var wire 1 c reset $end
$var reg 1 z Q $end
$upscope $end
$upscope $end
$scope begin dff[7] $end
$var parameter 4 { i $end
$scope module D $end
$var wire 1 | D $end
$var wire 1 a clk $end
$var wire 1 b en $end
$var wire 1 c reset $end
$var reg 1 } Q $end
$upscope $end
$upscope $end
$scope begin dff[8] $end
$var parameter 5 ~ i $end
$scope module D $end
$var wire 1 !" D $end
$var wire 1 a clk $end
$var wire 1 b en $end
$var wire 1 c reset $end
$var reg 1 "" Q $end
$upscope $end
$upscope $end
$scope begin dff[9] $end
$var parameter 5 #" i $end
$scope module D $end
$var wire 1 $" D $end
$var wire 1 a clk $end
$var wire 1 b en $end
$var wire 1 c reset $end
$var reg 1 %" Q $end
$upscope $end
$upscope $end
$scope begin dff[10] $end
$var parameter 5 &" i $end
$scope module D $end
$var wire 1 '" D $end
$var wire 1 a clk $end
$var wire 1 b en $end
$var wire 1 c reset $end
$var reg 1 (" Q $end
$upscope $end
$upscope $end
$scope begin dff[11] $end
$var parameter 5 )" i $end
$scope module D $end
$var wire 1 *" D $end
$var wire 1 a clk $end
$var wire 1 b en $end
$var wire 1 c reset $end
$var reg 1 +" Q $end
$upscope $end
$upscope $end
$scope begin dff[12] $end
$var parameter 5 ," i $end
$scope module D $end
$var wire 1 -" D $end
$var wire 1 a clk $end
$var wire 1 b en $end
$var wire 1 c reset $end
$var reg 1 ." Q $end
$upscope $end
$upscope $end
$scope begin dff[13] $end
$var parameter 5 /" i $end
$scope module D $end
$var wire 1 0" D $end
$var wire 1 a clk $end
$var wire 1 b en $end
$var wire 1 c reset $end
$var reg 1 1" Q $end
$upscope $end
$upscope $end
$scope begin dff[14] $end
$var parameter 5 2" i $end
$scope module D $end
$var wire 1 3" D $end
$var wire 1 a clk $end
$var wire 1 b en $end
$var wire 1 c reset $end
$var reg 1 4" Q $end
$upscope $end
$upscope $end
$scope begin dff[15] $end
$var parameter 5 5" i $end
$scope module D $end
$var wire 1 6" D $end
$var wire 1 a clk $end
$var wire 1 b en $end
$var wire 1 c reset $end
$var reg 1 7" Q $end
$upscope $end
$upscope $end
$upscope $end
$upscope $end
$enddefinitions $end
$comment Show the parameter values. $end
$dumpall
b1111 5"
b1110 2"
b1101 /"
b1100 ,"
b1011 )"
b1010 &"
b1001 #"
b1000 ~
b111 {
b110 x
b101 u
b100 r
b11 o
b10 l
b1 i
b0 f
b11000011010100000 _
b1010 ^
b111 Z
b110 W
b101 T
b100 Q
b11 N
b10 K
b1 H
b0 E
b11 =
b10 :
b1 7
b0 4
b10 ,
b1 )
b0 &
$end
#0
$dumpvars
x7"
x6"
x4"
x3"
x1"
x0"
x."
x-"
x+"
x*"
x("
x'"
x%"
x$"
x""
x!"
x}
x|
xz
xy
xw
xv
xt
xs
xq
xp
xn
xm
xk
xj
xh
xg
bx e
bx d
xc
xb
0a
bx `
bx ]
x\
z[
xY
zX
xV
zU
xS
zR
xP
zO
xM
zL
xJ
zI
xG
zF
bx D
zC
zB
zA
bz @
x?
z>
x<
z;
x9
z8
x6
z5
bx 3
z2
z1
z0
bz /
x.
z-
x+
z*
x(
z'
bx %
z$
z#
z"
bz !
$end
#10
1a
#20
0g
0j
0m
0p
0s
0v
0y
0|
0!"
0$"
0'"
0*"
0-"
00"
03"
06"
0a
0c
0b
b0 `
b0 d
#30
1a
#40
1g
1j
0a
1b
b11 `
b11 d
#50
1h
1k
0n
0q
0t
0w
0z
0}
0""
0%"
0("
0+"
0."
01"
04"
b11 ]
b11 e
07"
1a
#60
0g
0a
0b
b10 `
b10 d
#70
1a
#80
1g
0j
1m
1p
0a
b1101 `
b1101 d
#90
1a
#100
xg
xj
xm
xp
xs
xv
xy
x|
x!"
x$"
x'"
x*"
x-"
x0"
x3"
x6"
0a
1c
bx `
bx d
#110
1a
#120
0a
0c
