components/register/register16bit_tb.v
// Created by Kavan Heppenstall, 22/08/2024

`timescale 1ns/1ns
`include "register.v"

module tb;

parameter PERIOD = 10;
parameter RUNTIME = 100000;

reg clk;

reg [15:0] D;
reg reset;

wire [15:0] Q;

register16bit dut(.D(D), .clk(clk), .reset(reset), .Q(Q));

initial begin
    $display("starting simulation");
    clk = 0;
end

always begin
    if ($time > RUNTIME) begin
        $finish;
    end else begin
        #PERIOD clk = ~clk;
    end
end

initial begin

    $dumpfile("register16bit_tb.vcd");
    $dumpvars;

end

initial begin // Test Cases
    
    #20;

    D = 16'h0000; reset = 1'b0; #20;
    D = 16'h0003; reset = 1'b0; #20;
    D = 16'h0002; reset = 1'b0; #20;
    D = 16'h000D; reset = 1'b0; #20;
    reset = 1'b1; #20;
    
    #20;    


    $display("end simulation");
end



endmodule

components/register/register.v
// Created by Kavan Heppenstall, 22/08/2024

module dflipflop(D, clk, reset, Q);

input D, clk, reset;

output reg Q;


always @(posedge clk) begin
    
    if (reset) begin
        
        Q <= 1'b0;

    end else begin
        
        Q <= D;

    end

end


endmodule

module register16bit(D, clk, reset, Q);

input [15:0] D;
input clk, reset;

output [15:0] Q;

genvar i;
generate
    for (i = 0; i < 16; i = i + 1) begin : gen_flipflops
        dflipflop D (
            .D(D[i]),
            .clk(clk),
            .reset(reset),
            .Q(Q[i])
        );
    end
endgenerate


endmodule

module register8bit(D, clk, Q, reset);

input [7:0] D;
input clk, reset;

output [7:0] Q;

genvar i;
generate
    for (i = 0; i < 8; i = i + 1) begin : gen_flipflops
        dflipflop D (
            .D(D[i]),
            .clk(clk),
            .reset(reset),
            .Q(Q[i])
        );
    end
endgenerate


endmodule

components/register/register16bit_tb.vcd
$date
	Thu Aug 22 20:32:54 2024
$end
$version
	Icarus Verilog
$end
$timescale
	1ns
$end
$scope module register8bit $end
$var wire 8 ! D [7:0] $end
$var wire 1 " clk $end
$var wire 1 # reset $end
$var wire 8 $ Q [7:0] $end
$scope begin gen_flipflops[0] $end
$var parameter 2 % i $end
$scope module D $end
$var wire 1 & D $end
$var wire 1 " clk $end
$var wire 1 # reset $end
$var reg 1 ' Q $end
$upscope $end
$upscope $end
$scope begin gen_flipflops[1] $end
$var parameter 2 ( i $end
$scope module D $end
$var wire 1 ) D $end
$var wire 1 " clk $end
$var wire 1 # reset $end
$var reg 1 * Q $end
$upscope $end
$upscope $end
$scope begin gen_flipflops[2] $end
$var parameter 3 + i $end
$scope module D $end
$var wire 1 , D $end
$var wire 1 " clk $end
$var wire 1 # reset $end
$var reg 1 - Q $end
$upscope $end
$upscope $end
$scope begin gen_flipflops[3] $end
$var parameter 3 . i $end
$scope module D $end
$var wire 1 / D $end
$var wire 1 " clk $end
$var wire 1 # reset $end
$var reg 1 0 Q $end
$upscope $end
$upscope $end
$scope begin gen_flipflops[4] $end
$var parameter 4 1 i $end
$scope module D $end
$var wire 1 2 D $end
$var wire 1 " clk $end
$var wire 1 # reset $end
$var reg 1 3 Q $end
$upscope $end
$upscope $end
$scope begin gen_flipflops[5] $end
$var parameter 4 4 i $end
$scope module D $end
$var wire 1 5 D $end
$var wire 1 " clk $end
$var wire 1 # reset $end
$var reg 1 6 Q $end
$upscope $end
$upscope $end
$scope begin gen_flipflops[6] $end
$var parameter 4 7 i $end
$scope module D $end
$var wire 1 8 D $end
$var wire 1 " clk $end
$var wire 1 # reset $end
$var reg 1 9 Q $end
$upscope $end
$upscope $end
$scope begin gen_flipflops[7] $end
$var parameter 4 : i $end
$scope module D $end
$var wire 1 ; D $end
$var wire 1 " clk $end
$var wire 1 # reset $end
$var reg 1 < Q $end
$upscope $end
$upscope $end
$upscope $end
$scope module tb $end
$var wire 16 = Q [15:0] $end
$var parameter 32 > PERIOD $end
$var parameter 32 ? RUNTIME $end
$var reg 16 @ D [15:0] $end
$var reg 1 A clk $end
$var reg 1 B reset $end
$scope module dut $end
$var wire 16 C D [15:0] $end
$var wire 1 A clk $end
$var wire 1 B reset $end
$var wire 16 D Q [15:0] $end
$scope begin gen_flipflops[0] $end
$var parameter 2 E i $end
$scope module D $end
$var wire 1 F D $end
$var wire 1 A clk $end
$var wire 1 B reset $end
$var reg 1 G Q $end
$upscope $end
$upscope $end
$scope begin gen_flipflops[1] $end
$var parameter 2 H i $end
$scope module D $end
$var wire 1 I D $end
$var wire 1 A clk $end
$var wire 1 B reset $end
$var reg 1 J Q $end
$upscope $end
$upscope $end
$scope begin gen_flipflops[2] $end
$var parameter 3 K i $end
$scope module D $end
$var wire 1 L D $end
$var wire 1 A clk $end
$var wire 1 B reset $end
$var reg 1 M Q $end
$upscope $end
$upscope $end
$scope begin gen_flipflops[3] $end
$var parameter 3 N i $end
$scope module D $end
$var wire 1 O D $end
$var wire 1 A clk $end
$var wire 1 B reset $end
$var reg 1 P Q $end
$upscope $end
$upscope $end
$scope begin gen_flipflops[4] $end
$var parameter 4 Q i $end
$scope module D $end
$var wire 1 R D $end
$var wire 1 A clk $end
$var wire 1 B reset $end
$var reg 1 S Q $end
$upscope $end
$upscope $end
$scope begin gen_flipflops[5] $end
$var parameter 4 T i $end
$scope module D $end
$var wire 1 U D $end
$var wire 1 A clk $end
$var wire 1 B reset $end
$var reg 1 V Q $end
$upscope $end
$upscope $end
$scope begin gen_flipflops[6] $end
$var parameter 4 W i $end
$scope module D $end
$var wire 1 X D $end
$var wire 1 A clk $end
$var wire 1 B reset $end
$var reg 1 Y Q $end
$upscope $end
$upscope $end
$scope begin gen_flipflops[7] $end
$var parameter 4 Z i $end
$scope module D $end
$var wire 1 [ D $end
$var wire 1 A clk $end
$var wire 1 B reset $end
$var reg 1 \ Q $end
$upscope $end
$upscope $end
$scope begin gen_flipflops[8] $end
$var parameter 5 ] i $end
$scope module D $end
$var wire 1 ^ D $end
$var wire 1 A clk $end
$var wire 1 B reset $end
$var reg 1 _ Q $end
$upscope $end
$upscope $end
$scope begin gen_flipflops[9] $end
$var parameter 5 ` i $end
$scope module D $end
$var wire 1 a D $end
$var wire 1 A clk $end
$var wire 1 B reset $end
$var reg 1 b Q $end
$upscope $end
$upscope $end
$scope begin gen_flipflops[10] $end
$var parameter 5 c i $end
$scope module D $end
$var wire 1 d D $end
$var wire 1 A clk $end
$var wire 1 B reset $end
$var reg 1 e Q $end
$upscope $end
$upscope $end
$scope begin gen_flipflops[11] $end
$var parameter 5 f i $end
$scope module D $end
$var wire 1 g D $end
$var wire 1 A clk $end
$var wire 1 B reset $end
$var reg 1 h Q $end
$upscope $end
$upscope $end
$scope begin gen_flipflops[12] $end
$var parameter 5 i i $end
$scope module D $end
$var wire 1 j D $end
$var wire 1 A clk $end
$var wire 1 B reset $end
$var reg 1 k Q $end
$upscope $end
$upscope $end
$scope begin gen_flipflops[13] $end
$var parameter 5 l i $end
$scope module D $end
$var wire 1 m D $end
$var wire 1 A clk $end
$var wire 1 B reset $end
$var reg 1 n Q $end
$upscope $end
$upscope $end
$scope begin gen_flipflops[14] $end
$var parameter 5 o i $end
$scope module D $end
$var wire 1 p D $end
$var wire 1 A clk $end
$var wire 1 B reset $end
$var reg 1 q Q $end
$upscope $end
$upscope $end
$scope begin gen_flipflops[15] $end
$var parameter 5 r i $end
$scope module D $end
$var wire 1 s D $end
$var wire 1 A clk $end
$var wire 1 B reset $end
$var reg 1 t Q $end
$upscope $end
$upscope $end
$upscope $end
$upscope $end
$enddefinitions $end
$comment Show the parameter values. $end
$dumpall
b1111 r
b1110 o
b1101 l
b1100 i
b1011 f
b1010 c
b1001 `
b1000 ]
b111 Z
b110 W
b101 T
b100 Q
b11 N
b10 K
b1 H
b0 E
b11000011010100000 ?
b1010 >
b111 :
b110 7
b101 4
b100 1
b11 .
b10 +
b1 (
b0 %
$end
#0
$dumpvars
xt
xs
xq
xp
xn
xm
xk
xj
xh
xg
xe
xd
xb
xa
x_
x^
x\
x[
xY
xX
xV
xU
xS
xR
xP
xO
xM
xL
xJ
xI
xG
xF
bx D
bx C
xB
0A
bx @
bx =
x<
z;
x9
z8
x6
z5
x3
z2
x0
z/
x-
z,
x*
z)
x'
z&
bx $
z#
z"
bz !
$end
#10
1A
#20
0F
0I
0L
0O
0R
0U
0X
0[
0^
0a
0d
0g
0j
0m
0p
0s
0A
0B
b0 @
b0 C
#30
0t
0q
0n
0k
0h
0e
0b
0_
0\
0Y
0V
0S
0P
0M
0J
b0 =
b0 D
0G
1A
#40
1F
1I
0A
b11 @
b11 C
#50
1G
b11 =
b11 D
1J
1A
#60
0F
0A
b10 @
b10 C
#70
b10 =
b10 D
0G
1A
#80
1F
0I
1L
1O
0A
b1101 @
b1101 C
#90
1G
0J
1M
b1101 =
b1101 D
1P
1A
#100
0A
1B
#110
0P
0M
b0 =
b0 D
0G
1A
